Workbook

Sheet Information
A1: Ekonomisystem, UPP-2025/047 | C1: Anbudsgivare:
A3: Krav
A4: Uppfyllande av krav ska kunna verifieras på begäran. Kraven (samtliga ska-krav och de uppfyllda bör-kraven) ska vara uppfyllda vid anbudsinlämningstillfället, om inte annat uttryckligen framgår enligt kravformuleringen
A6: Ska-krav
A7: Samtliga obligatoriska krav (ska-krav) i upphandlingen ska uppfyllas för att anbudet ska vara kvalificerat. I och med inlämnade av anbud accepterar anbudsgivaren samtliga ställda ska-krav i upphandlingsdokumenten. Uppfyllande ska kunna verifieras på begäran. Samtliga krav som i kolumn C markerade som "Ska-krav" utgör ska-krav.
A9: Bör-krav
A10: Leverantören fyller i om de anser att de uppfyller bör-kravet eller inte.
A11: Avdrag för uppfyllda bör-krav visas om anbudsgivaren väljer "ja" vid respektive bör-krav.
A12: De bör-krav som anges vara uppfyllda ingår i anbudet och utgör således, tillsammans med ska-kraven, en del av avtalsinnehållet/åtagande enligt avtalet. Samtliga krav som i kolumn C markerade som "Bör-krav" utgör bör-krav.
A14: Optioner
A15: Optioner utgör ska-krav för anbudsgivaren.
A16: Beställaren har rätt, dock är inte är förpliktad, att använda optionen under valfri period under avtalstiden

Sheet 1. Generellt
A1: Ekonomisystem, UPP-2025/047 | D1: Anbudsgivare: | E1: =Information!D1 -> 0
A3: 1 | B3: GENERELLT | C3: Typ av krav | D3: Uppfylls bör-kravet? | E3: Bör-kravet vikt/poäng | F3: Avdrag för uppfyllda bör-krav | G3: ja | H3: nej
A4: Nr | B4: Område/funktion
A5: 1.1 | B5: Allmänt
A6: 1.1.1 | B6: Leverantören ska tillhandahålla en komplett leverans av ekonomisystem som tjänst (SaaS), inklusive licenser, drift, service och support (IT-tjänsten), vidareutveckling samt tillkommande konsulttjänster. | C6: Ska-krav
A7: 1.1.2 | B7: Leverantören ska ha ett helhetsansvar för hela IT-tjänsten inkl. eventuella tredjepartsprodukter. | C7: Ska-krav
A8: 1.1.3 | B8: Det ska finnas en pedagogisk kunskapsdatabas och/eller handbok som innehåller relevant hjälp för användare, inklusive systemadministratörer. | C8: Ska-krav
A9: 1.1.4 | B9: Svenska ska vara det språk som används vid funktionsutförande i IT-tjänsten i bl.a. menyer, hjälpfunktioner, lathundar m.m. Teknisk dokumentation ska vara på svenska eller engelska. | C9: Ska-krav
A10: 1.1.5 | B10: IT-tjänsten ska innehålla hjälptexter och/eller instuktioner. Dessa ska beskriva hur man kan lösa uppgiften. | C10: Ska-krav
A11: 1.1.6 | B11: Beställaren ska ha exklusiv äganderätt till all data/information som Beställaren skapat i IT-tjänsten. | C11: Ska-krav
A12: 1.1.7 | B12: Leverantören ska garantera att Beställarens data aldrig används utan Beställarens tillstånd till något annat än leverans av avtalad tjänst. | C12: Ska-krav
A13: 1.1.8 | B13: Standarfunktionaliteten i IT-tjänsten ska överensstämma med tryckfrihetsförordningen (TF), förvaltningslagen, offentlighets- och sekretesslagen, arkivlagen samt GDPR. Leverantören ska utan dröjsmål anpassa IT-tjänsten när sådana lagar ändras. | C13: Ska-krav
A14: 1.1.9 | B14: IT-tjänsten ska ha en generell funktion för sammanställning av en persons samlade uppgifter i databasen så att redovisning enligt GDPR kan tillgodoses. Funktionen ska vara strikt behörighetsstyrd till ett fåtal personer. | C14: Ska-krav
A15: 1.1.10 | B15: IT-tjänsten ska ha funktion för att anonymisera personuppgifter. | C15: Ska-krav
A16: 1.1.11 | B16: IT-tjänsten ska uppfylla lokala legala regelverk och redovisningsmässiga sedvänjor i Sverige. Så som LKBR, RKR, KL | C16: Ska-krav
A17: 1.1.12 | B17: Leverantören ska kontinuerligt utveckla IT-tjänsten för att tillgodose de krav som lagar och myndigheter ställer på kommunal redovisning i Sverige/EU. | C17: Ska-krav
... A25: 1.1.21 | B25: IT-tjänsten ska ha funktion för att hantera återbetalningar, både inrikes och utrikes, enligt kända standarder (minst ISO 20022). | C25: Ska-krav
A26: 1.1.22 | B26: IT-tjänsten bör ha funktion för att automatiskt ersätta en stängd konteringsdimension som initierats i IT-tjänsten eller importerats från ett av Beställarens försystem. | C26: Bör-krav | E26: =IF(D26=J28,5,(IF(D26=J29,0,0))) -> 0 | F26: =(Jämförelsesumma!$E$6/Jämförelsesumma!$F$6)*E26 -> 0
A27: 1.1.23 | B27: I IT-tjänsten ska det vara möjligt att bifoga dokument kopplade till verifikationer i samtliga processer/moduler | C27: Ska-krav
A28: 1.1.24 | B28: IT-tjänsten ska ha funktion för att bokföra automatiskt inlästa filer i den period som framgår i filen | C28: Ska-krav | J28: ja
A29: 1.1.25 | B29: IT- Tjänsten bör ha funktionalitet att per automatik hämta uppmärkta verifikationsunderlag från uppsatt importkatalog och koppla dem till respektive verifikation. | C29: Bör-krav | E29: =IF(D29=J28,5,(IF(D29=J29,0,0))) -> 0 | F29: =(Jämförelsesumma!$E$6/Jämförelsesumma!$F$6)*E29 -> 0 | J29: Nej | O29: Ja, uppdatering sker minst årligen av leverantören
A30: 1.1.26 | B30: IT-Tjänsten ska ha funktionen för att manuellt skapa nya postnummer, både inrikes och utrikes. | C30: Ska-krav | O30: Ja, uppdatering sker minst månadsvis av leverantören
A31: 1.1.27 | B31: IT-Tjänsten bör tillhandahålla ett av leverantören regelbundet uppdaterat postnummerregister (Svenska) | C31: Bör-krav | E31: =IF(D31="Ja, uppdatering sker minst årligen av leverantören", 1, IF(D31="Ja, uppdatering sker minst månadsvis av leverantören", 2, 0)) -> 0 | F31: =(Jämförelsesumma!$E$6/Jämförelsesumma!$F$6)*E31 -> 0 | O31: Nej
A32: 1.2 | B32: Valideringar och systemkontroll
A33: 1.2.1 | B33: Enskilda moduler/processer (såsom kundreskontra, leverantörsreskontra) i IT-Tjänsten ska kunna stängas vid olika tidpunkter vid periodbryt. | C33: Ska-krav
A34: 1.2.2 | B34: IT-tjänsten ska ha funktion så att Beställaren kan påverka vissa fält, om de ska vara obligatoriska eller ej, samt vilka giltiga värden som kan användas. | C34: Ska-krav
A35: 1.2.3 | B35: IT-tjänsten ska ha funktion för att logga transaktioner och ändring av registerinformation (ex. kunduppgifter, leverantörsuppgifter etc.) med användar-id och tidsstämpel, tidigare värde och ändrat till värde. | C35: Ska-krav
A36: 1.2.4 | B36: Uppdatering av IT-tjänsten ska ske i nära realtid och inga journaler behöver köras för att se transaktioner/data/resultat i IT-tjänsten. | C36: Ska-krav
A37: 1.2.5 | B37: IT-tjänsten bör ha stöd för avisering av inaktiva användare. Exempelvis om användaren inte varit inloggad på ett år. | C37: Bör-krav | E37: =IF(D37=G3,1,0) -> 0 | F37: =(Jämförelsesumma!$E$6/Jämförelsesumma!$F$6)*E37 -> 0
A38: 1.2.6 | B38: IT-tjänsten bör ha stöd för avisering av inaktiva värden. Exempelvis en aktivitetskod som ej använts på ett år. | C38: Bör-krav | E38: =IF(D38="ja",3,0) -> 0 | F38: =(Jämförelsesumma!$E$6/Jämförelsesumma!$F$6)*E38 -> 0
A39: 1.2.7 | B39: Alla moduler/processer (såsom kundreskontra, leverantörsreskontra) ska dela på gemensamma grundregister (master data) för kund, leverantör och kontoplan. | C39: Ska-krav
A40: 1.2.8 | B40: IT-Tjänsten bör ha funktion så att vissa roller kan schemalägga periodstängningar | C40: Bör-krav | E40: =IF(D40="ja",5,0) -> 0 | F40: =(Jämförelsesumma!$E$6/Jämförelsesumma!$F$6)*E40 -> 0
A41: 1.3 | B41: Valutahantering
A42: 1.3.1 | B42: IT-tjänsten ska kunna hantera svensk valuta. | C42: Ska-krav
A43: 1.3.2 | B43: IT-tjänsten ska ha funktion för att hantera valfritt antal valutor, samt kunna omvärdera balansposter vid valda tillfällen. | C43: Ska-krav
A44: 1.3.3 | B44: IT-tjänsten ska ha funktion för minst två valutor på varje transaktion. | C44: Ska-krav
A45: 1.4 | B45: Rapporter
A46: 1.4.1 | B46: IT-tjänsten ska ha funktion för att bygga och presentera både generella och användarspecifika rapporter i samtliga moduler/processer. | C46: Ska-krav
A47: 1.4.2 | B47: IT-tjänsten ska har funktion för att ställa frågor nära realtid i alla moduler/processer (såsom kundreskontra, leverantörsreskontra). | C47: Ska-krav
A48: 1.4.3 | B48: IT-tjänsten ska ha funktion för att göra dynamiska sökningar på relevanta fält i IT-tjänsten. | C48: Ska-krav
A49: 1.4.4 | B49: IT-tjänsten ska ha en blankettgenerator som kan användas för att skapa layouter för systemgenererade dokument (t.ex. kundfaktura, prislistor och inköpsordrar i enlighet med kundens grafiska layout och profil). | C49: Ska-krav
A50: 1.4.5 | B50: IT-tjänsten ska ha funktion för drill-down och drill-around mellan olika delar i IT-tjänsten. | C50: Ska-krav
A51: 1.4.6 | B51: IT-tjänsten ska tillhandahålla information om fel som underlättar avhjälpning (t ex ej matchade inbetalningar, ej fakturerade ordrar, filhanteringsproblem). | C51: Ska-krav
A52: 1.4.7 | B52: Det ska finnas möjlighet att ta ut rapport på valfria verfikationer med tillhörande bilagor | C52: Ska-krav
A53: 1.4.8 | B53: IT-tjänsten ska ha en flexibel och intuitiv rapportfunktion. | C53: Ska-krav
A54: 1.4.9 | B54: IT-tjänsten ska ha funktion för att anpassa vyer till roller. | C54: Ska-krav
A55: 1.4.10 | B55: Det ska finns möjlighet att styra vilka rapporter respektive roll har tillgång till. | C55: Ska-krav
A56: 1.4.11 | B56: IT-tjänsten ska ha funktion att visa information kring användarna och hur de använder IT-tjänsten. | C56: Ska-krav
A57: 1.4.12 | B57: IT-tjänsten ska ha funktion för att skapa varningar som visas/levereras till valda roller. Exempelvis en varning till systemadministratör om att en fil, som har lästs in automatiskt, innehåller fel. | C57: Ska-krav
A58: 1.5 | B58: Säkerhet
A59: 1.5.1 | B59: Leverantören ska uppfylla krav gällande säkerhet i enlighet med vad som anges i Bilaga 3 – Säkerhet | C59: Ska-krav
A60: 1.5.2 | B60: Leverantörens redovisning över uppfyllnad av krav i Bilaga Säkerhet, punkt 5, ”Ställe för avtalets fullgörande” enligt Leverantörens anbud, tillsammans med Personuppgiftsbiträdesavtal inklusive p.7 i Bilaga Instruktion, ska reglera hur personuppgifter hanteras i IT-tjänsten samt var lagring av personuppgifter sker (land/företag etc), vilka eventuella underbiträden och i vilket sammanhang hanterar Beställarens personuppgifter, samt var och hur dessa lagrar personuppgifter. Leverantörens redovisning enligt ovan ingår i Leverantörens åtagande | C60: Ska-krav
A61: 1.6 | B61: Koncernregister
A62: 1.6.1 | B62: IT-tjänsten ska ha funktion för flera juridiska enheter. Flerföretagsinstallation. | C62: Ska-krav
A63: 1.6.2 | B63: IT-tjänsten ska ha funktion för administration av koncerngemensamma register för kunder, leverantörer och produkter - men med möjlighet att kunna särskilja bolagsspecifika detaljer såsom leveransvillkor, avtalsvillkor, prislistor, kontaktpersoner och adresser. | C63: Ska-krav
A64: 1.6.3 | B64: IT-tjänsten ska ha funktion för internhandel (inter-company) mellan olika juridiska enheter i samma installation. | C64: Ska-krav
A65: 1.7 | B65: Avsluta användandet av IT-tjänsten
A66: 1.7.1 | B66: All Beställaren skapad data som finns i IT-tjänsten ska exporteras till Huddinge kommun vid avslut av användandet av IT-tjänsten, oavsett vad anledningen till avslut är utan extra kostnad. Datan ska tillhandahållas inom två (2) månader | C66: Ska-krav
A67: 1.7.2 | B67: Dataexporten ska vara i ett format som möjliggör återanvändning av informationen. | C67: Ska-krav
A68: 1.7.3 | B68: Vid avslut av användandet av IT-tjänsten, oavsett vad anledningen till avslut är, ska Beställaren få tillgång till data så att Beställaren kan uppfylla gällande redovisningslagstiftning. Exempelvis genom export/migrering av relevant data i standardiserad format som är kompatibel till på marknaden vedertagna databaser och/eller leverantörsreskontrasystem, genom tillhandahållande av ett verktyg/begränsad behörighet som möjliggör återsökning under hela arkiveringstiden, eller på annat för Beställaren tillgängligt strukrurerat och sökbart sätt. | C68: Ska-krav
A69: 1.7.4 | B69: Leverantören ska varken äga rätt att disponera, avslöja, informera om, vidareförmedla eller på annat sätt nyttja det data som finns i IT-tjänsten efter avslut av IT-tjänsten. | C69: Ska-krav
A70: 1.8 | B70: Användbarhet | J70: Ja, men endast leverantören kan anpassa
A71: 1.8.1 | B71: IT- Tjänsten bör kunna anpassas efter användarens behov. Exempelvis personligt anpassade arbetsytor | C71: Bör-krav | E71: =IF(D71=J70,1,(IF(D71=J71,2,(IF(D71=J72,1,0))))) -> 0 | F71: =(Jämförelsesumma!$E$6/Jämförelsesumma!$F$6)*E71 -> 0 | J71: Ja, men endast vissa roller kan göra detta | N71: Ja, endast leverantören = 1p Ja, endast vissa roller = 2p. Ja, alla användare = 4p
A72: 1.9 | B72: Personuppgifter | J72: Ja, Användaren kan göra detta själv oavsett roll
A73: 1.9.1 | B73: Personuppgifter ska behandlas enligt Bilaga 2 Personuppgiftsbiträdesavtal | C73: Ska-krav
C75: Summa Börkravspoäng: | E75: =SUM(E6:E73) -> 0

Sheet 2. Redovisning
A1: ='1. Generellt'!A1 -> Ekonomisystem, UPP-2025/047 | C1: Anbudsgivare: | D1: =Information!D1 -> 0 | H1: ja | I1: nej
A3: 2 | B3: Redovisning | C3: Typ av krav | D3: Uppfylls bör-kravet? | E3: Bör-kravet vikt/poäng | F3: Avdrag för uppfyllda bör-krav
A4: Nr | B4: Område/funktion
A5: 2.1 | B5: Allmänt
A6: 2.1.1 | B6: IT-tjänsten ska ha funktion för att arbeta med flera bokföringsår öppna samtidigt. | C6: Ska-krav
A7: 2.1.2 | B7: IT-tjänsten ska ha funktion för att hantera flera olika verifikationsserier eller verifikationstyp parallellt (bl. a. för att särskilja olika försystem/moduler och transaktionstyper). | C7: Ska-krav
A8: 2.1.3 | B8: IT-tjänsten ska ha inbyggda datumkontroller mot registrering i stängda perioder. | C8: Ska-krav
A9: 2.1.4 | B9: IT-tjänsten ska ha funktion för automatisk överföring av ingående och utgående balanser. | C9: Ska-krav
A10: 2.1.5 | B10: I IT-tjänsten ska det gå att ha olika kontoplaner per juridisk enhet med unika summerade kontoklasser. | C10: Ska-krav
A11: 2.1.6 | B11: IT-tjänsten ska ha funktion för att låsa konto för automatisk bokföring. Exempelvis låsa leverantörs skulder eller hyresfordran. | C11: Ska-krav
A12: 2.1.7 | B12: IT-tjänsten ska ha funktion för kontoavstämning | C12: Ska-krav
A13: 2.2 | B13: Registrering
A14: 2.2.1 | B14: IT-tjänsten ska ha funktion för att automatiskt vända interimsbokningar i efterföljande period. | C14: Ska-krav
A15: 2.2.2 | B15: IT-tjänsten ska ha funktion för att periodisera kostnader/intäkter med automatisk avräkning mot interimsskuld/interimsfordring. | C15: Ska-krav
A16: 2.2.3 | B16: IT-tjänsten ska ha funktion för att lägga upp olika periodiseringsnycklar. | C16: Ska-krav
A17: 2.2.4 | B17: IT-tjänsten ska ha funktioner för automatfördelning (påslag/fördelningar) av konteringar. Exempelvis påslag på löneskatt för pensioner/fördelning av OH-kostnader. | C17: Ska-krav
A18: 2.2.5 | B18: IT-tjänsten ska ha funktion för att styra automatkontering på valfri kombination av konteringsdelar. | C18: Ska-krav
A19: 2.2.6 | B19: IT-tjänsten ska ha funktion för att kunna göra automatfördelningar/påslag både triggade på specifika koddelskombinationer per verifikation men även fördela summan av ett antal verifikationer. | C19: Ska-krav
A20: 2.2.7 | B20: IT-tjänsten ska ha funktion för att registrera manuellt verifikat. | C20: Ska-krav
A21: 2.2.8 | B21: IT-tjänsten ska ha funktion för manuell omkontering av valfria rader med full spårbarhet | C21: Ska-krav | G21: ändringen finns i loggen//JP
A22: 2.2.9 | B22: IT-tjänsten ska ha funktion för att makulera registrerade verifikat med full spårbarhet. | C22: Ska-krav
A23: 2.2.10 | B23: IT-tjänsten ska ha funktion för att läsa in bokföringsorder från Excel | C23: Ska-krav
A24: 2.2.11 | B24: IT-Tjänsten bör ha funktion så att vissa roller kan schemalägga periodstängningar | C24: Bör-krav | E24: =IF(D24=H1,5,0) -> 0 | F24: =(Jämförelsesumma!$E$6/Jämförelsesumma!$F$6)*E24 -> 0
A25: 2.3 | B25: Kontoplan och konteringsregler
A26: 2.3.1 | B26: IT-tjänsten ska ha kontoplan (Kommun-BAS) med konto och ytterligare minst sju (7) redovisningsdimensioner. Dessa ska kunna anpassas och namnsättas efter Beställarens ekonomimodell. | C26: Ska-krav
A27: 2.3.2 | B27: IT-tjänsten ska ha funktion för nummerserie för kontoplan och redovisningsdimensioner som kan hantera minimum nio positioner, med alfanumeriskt stöd. | C27: Ska-krav
A28: 2.3.3 | B28: IT-tjänsten ska ha möjlighet att bokföra verifikat på värde och/eller volym. | C28: Ska-krav
A29: 2.3.4 | B29: IT-tjänsten ska ha funktion/ möjlighet att sätta villkor på konton och konteringsdimensioner (sambandskontroller) mot övriga dimensioner. | C29: Ska-krav
A30: 2.3.5 | B30: Beställaren ska kunna lägga upp, ändra och stänga samtliga konteringsdimensioner. | C30: Ska-krav | G30: ändringen finns i loggen//JP
A31: 2.4 | B31: Inläsning av budget och prognos
A32: 2.4.1 | B32: IT-tjänsten ska ha funktionalitet för att registrera in årsbudget per månad. | C32: Ska-krav
A33: 2.4.2 | B33: I IT-tjänsten ska det finns funktion att läsa in flera versioner av budget och prognos | C33: Ska-krav
A34: 2.4.3 | B34: IT-tjänsten ska ha funktionalitet för att registrera in prognoser på månadsbasis (separat från budget). | C34: Ska-krav
A35: 2.4.4 | B35: IT-tjänsten ska ha funktion för att registrera budgeten på valfritt antal koddelar. | C35: Ska-krav
A36: 2.4.5 | B36: IT-tjänsten ska ha funktion för att registrera in budget och prognos från Excel. | C36: Ska-krav
A37: 2.4.6 | B37: IT-tjänsten ska ha funktion för att skapa en budget distribuerat hos kostnadsställeansvariga och konsolidera denna till en totalbudget för organisationen. | C37: Ska-krav
A38: 2.4.7 | B38: IT-tjänsten ska ha funktion för att stödja arbetet med likviditetsprognoser. | C38: Ska-krav
A39: 2.5 | B39: Rapporter
A40: 2.5.1 | B40: IT-tjänsten ska ha funktion för likviditetsplanering (sammanställning av kassapåverkande transaktioner i framtiden). | C40: Ska-krav
A41: 2.5.2 | B41: IT-tjänsten ska ha funktion för att sammanställa momsrapportering enligt skattemyndighetens krav. | C41: Ska-krav
A42: 2.5.3 | B42: IT-tjänsten ska ha funktion för att söka ut information på samtliga koddelar, enskilt eller kombinerat med andra, i form av intervaller, listor, specifika koder etc. | C42: Ska-krav
A43: 2.5.4 | B43: IT-tjänsten ska ha funktion för att söka ut enskilda verifikationer eller summan av alla verifikationer för olika koddelar. | C43: Ska-krav
A44: 2.5.5 | B44: IT-tjänsten ska ha funktion för skapande av intrastatrapportering så som tex. SRU-koder och SCB-koder. | C44: Ska-krav
A45: 2.5.6 | B45: IT-tjänsten ska ha funktion för att beställa rapporter över både valfria perioder samt from-tom specifika datum. | C45: Ska-krav
A46: 2.5.7 | B46: IT-tjänsten ska ha funktion för att söka transaktioner på belopp, beloppsintervaller, periodintervaller och datumintervaller. | C46: Ska-krav
A47: 2.5.8 | B47: I rapportfunktionen ska det finnas möjlighet att dynamiskt styra vilka rad- och kolumnval som ingår i en redovisningsrapport. | C47: Ska-krav
A48: 2.5.9 | B48: IT-tjänsten ska ha funktion för att skapa rapporteringshierarkier för samtliga konteringsdimensioner. | C48: Ska-krav
A49: 2.5.10 | B49: IT-tjänsten ska ha funktion för att skapa beräknade kolumner i rapporteringen. | C49: Ska-krav
A50: 2.5.11 | B50: IT-tjänsten ska ha funktion för att se en sammanställning över periodiseringar på balanskonton. | C50: Ska-krav
A51: 2.5.12 | B51: IT-tjänsten ska ha funktion för att presentera rapport med olika värdetyper så som utfall, prognos, budget, projektutfall | C51: Ska-krav
... A53: 2.5.14 | B53: Leverantören ska kontinuerligt tillhandahålla uppdaterad RS-mall enligt SCBs krav. Inläsning ska kunna ske från IT-tjänst till mall. | C53: Ska-krav
C54: Summa Börkravspoäng: | E54: =SUM(E6:E53) -> 0

Sheet 3. Kundreskontra
A1: ='1. Generellt'!A1 -> Ekonomisystem, UPP-2025/047 | D1: Anbudsgivare: | E1: =Information!D1 -> 0
A3: 3 | B3: Kundreskontra | C3: Typ av krav | D3: Uppfylls bör-kravet? | E3: Bör-kravet vikt/poäng | F3: Avdrag för uppfyllda bör-krav
A4: Nr | B4: Område/funktion
A5: 3.1 | B5: Allmänt
A6: 3.1.1 | B6: IT-tjänsten ska ha funktion för manuell registrering av fakturor | C6: Ska krav
A7: 3.1.2 | B7: IT-tjänsten ska ha funktion för att i reskontran kunna skilja på koncerninterna och olika typer av externa kunder med separata kundfordringskonton. | C7: Ska-krav
A8: 3.1.3 | B8: IT-tjänsten ska ha funktion för differentierad kravhantering för olika typer av kunder. | C8: Ska-krav
A9: 3.1.4 | B9: IT-tjänsten ska ha funktion att i reskontran kunna se vilken försäljningsorder fakturan avser. | C9: Ska-krav
A10: 3.1.5 | B10: IT-tjänsten ska ha stöd för olika typer av elektroniskt fakturaformat (Peppol, svefaktura) | C10: Ska-krav
A11: 3.1.6 | B11: IT-tjänsten ska ha funktion för att ta ut fakturakopia i PDF format där det tydligt framgår att det är en fakturakopia. | C11: Ska-krav
A12: 3.1.7 | B12: IT-tjänsten ska ha funktion att kopiera befintlig order till ny order | C12: Ska-krav
A13: 3.1.8 | B13: IT-tjänsten ska ha funktion att skapa kreditfaktura utifrån tidigare order som ligger i kundreskontra. | C13: Ska-krav
A14: 3.1.9 | B14: Det ska vara möjligt i IT-tjänsten att direkt vid skapandet av kreditfaktura kvitta denna mot ursprungsfakturan. | C14: Ska-krav
A15: 3.1.10 | B15: IT-tjänsten ska ha funktion för förhandsgranskning av faktura, faktura ska visas och spegla den kommande skarpa fakturan. | C15: Ska-krav
A16: 3.1.11 | B16: IT-tjänsten ska ha funktion för att kreditfakturors förfallodatum sätts till fakturadagen | C16: Ska-krav
A17: 3.1.12 | B17: IT-tjänsten ska ha funktion för återkommande fakturering (kundabonnemang) med stöd för flera olika debiteringsperioder. | C17: Ska-krav
... A23: 3.1.17 | B23: IT-tjänsten ska ha funktion för "massfakturering" där ett och samma fakturaunderlag används för att skapa faktura till ett antal utvalda kunder. | C23: Ska-krav
A24: 3.1.18 | B24: IT-tjänsten bör ha funktion för att från Excel importera och skapa kundordrar/fakturor. | C24: Bör krav | E24: =IF(D24="ja",1,0) -> 0 | F24: =(Jämförelsesumma!$E$6/Jämförelsesumma!$F$6)*E24 -> 0 | H24: Ja | I24: Nej
A25: 3.1.19 | B25: IT-tjänsten ska ha funktion för att bifoga dokument till kundorder och som skickas med till kund vid fakturering. | C25: Ska-krav
A26: 3.1.20 | B26: IT-tjänsten ska ha funktion för att bifoga dokument till kundorder/faktura och som inte skickas med till kund vid fakturering. | C26: Ska-krav
A27: 3.1.21 | B27: IT-tjänsten ska ha funktion för att kunna ändra förfallodatum på faktura. | C27: Ska-krav
A28: 3.1.22 | B28: I IT-tjänsten ska det vara möjligt att göra testkörning samt göra rättningar i underlaget innan skarp körning, exempelvis vid fakturering, abonnemangskörning etc. | C28: Ska-krav
A29: 3.1.23 | B29: IT-tjänsten ska ha funktion för att kunna del- eller helkreditera fakturor och räntefakturor. | C29: Ska-krav
A30: 3.1.24 | B30: IT-tjänsten ska ha funktioner för att hantera hela autogiroflödet från medgivande till betalning | C30: Ska-krav
A31: 3.1.25 | B31: IT-tjänsten ska ha funktion för att varna för registrering av dubbletter. | C31: Ska-krav
A32: 3.1.26 | B32: Sytemet ska ha funktion för att varna vid inmatning av ologiska organisations- eller personnummer | C32: Ska-krav
A33: 3.1.27 | B33: IT-tjänsten ska kunna hantera av Migratiosverket tilldelade TF och samordningsnummer. | C33: Ska-krav
A34: 3.1.28 | B34: IT-tjänsten ska ha funktion att läsa in fakturaunderlag från externa system. Funktionen ska kunna ske både automatiskt och manuellt | C34: Ska-krav
A35: 3.1.29 | B35: IT-tjänsten ska ha funktion för att markera kunder som har skyddad identitet. | C35: Ska-krav
A36: 3.1.30 | B36: Det ska gå att markera sekretessbelagda/-markerade kunduppgifter, direkt i IT-tjänsten. | C36: Ska-krav
... A39: 3.1.33 | B39: IT-tjänsten ska ha stöd för hantera c/o adresser | C39: Ska-krav
A40: 3.1.34 | B40: Det bör finnas fritextfält på kundorder/faktura | C40: Bör krav | E40: =IF(D40="ja",1,0) -> 0 | F40: =(Jämförelsesumma!$E$6/Jämförelsesumma!$F$6)*E40 -> 0
A41: 3.1.35 | B41: Det bör vara möjligt att importera fritext till kundorder/faktura från försystem | C41: Bör krav | E41: =IF(D41="ja",2,0) -> 0 | F41: =(Jämförelsesumma!$E$6/Jämförelsesumma!$F$6)*E41 -> 0
A42: 3.1.36 | B42: IT-Tjänsten ska ha funktion för att skapa nya artiklar | C42: Ska-krav
A43: 3.1.37 | B43: IT-Tjänsten ska ha funktion för att skapa en konteringmall som kopplas mot en artikel | C43: Ska-krav
A44: 3.1.38 | B44: IT-Tjänsten ska ha funktion för avskrivningar av kundfordringar. | C44: Ska-krav
A45: 3.1.39 | B45: IT-Tjänsten ska ha funktion för att automatiskt skapa ett avskrivningsförslag utifrån överrenskomna kriterier. Avskrivning av kundfordringarna ska ske per automatik när förslaget har bekräftats | C45: Ska-krav
A46: 3.1.40 | B46: IT-Tjänsten ska ha funktion för att vid utvalda faktureringstillfällen ta bort möjligheten att skicka fakturorna för autogirodragning utan att de påverkar medgivandet som är registrerat på kunderna | C46: Ska-krav
A47: 3.1.41 | B47: IT-tjänsten bör ha funktion för att kunna klarmarkera kundfakturor som är på 0 Kr i slutet av månaden | C47: Bör krav | E47: =IF(D47="ja",2,0) -> 0 | F47: =(Jämförelsesumma!$E$6/Jämförelsesumma!$F$6)*E47 -> 0
A48: 3.1.42 | B48: It-Tjänsten ska leverera beställarens fakturor till beställarens valda fakturadistibutör oavsett valt leveranssätt | C48: Ska-krav | E48: =IF(D48="ja",5,0) -> 0 | F48: =(Jämförelsesumma!$E$6/Jämförelsesumma!$F$6)*E48 -> 0
A49: 3.1.43 | B49: IT-tjänsten bör tillhandahålla matchande fakturalayouter mellan system och utskrift. (Avser ej Peppol och Svefaktura layouter) | C49: Bör krav | E49: =IF(D49=H49,1,(IF(D49=I49,3,0))) -> 0 | F49: =(Jämförelsesumma!$E$6/Jämförelsesumma!$F$6)*E49 -> 0 | G49: ja, det går att anpassa delar av layouten = 1p ja, allt går att anpassa = 3p | H49: ja, det går att anpassa delar av layouten | I49: ja, allt går att anpassa | J49: nej
A50: 3.1.44 | B50: IT-Tjänsten ska leverera beställarens fakturor till beställarens valda fakturadistibutör oavsett valt leveranssätt | C50: Ska-krav
A51: 3.2 | B51: Kundregister
A52: 3.2.1 | B52: IT-tjänsten ska ha funktion för att läsa in och uppdatera kunduppgifter från externa system. Regler för matchning ska kunna göras på multipla fält. | C52: Ska-krav
A53: 3.2.2 | B53: IT-tjänsten ska ha funktion för att lägga upp nya kunder och uppdatera befintliga kunder manuellt. | C53: Ska-krav
A54: 3.2.3 | B54: IT-tjänsten ska ha funktion för att registrera koncernkod på kund (koncern/dotterföretag). | C54: Ska-krav
A55: 3.2.4 | B55: IT-tjänsten ska ha funktion för att registrera motpartskod på kund. Motpartskoden ska automatiskt läggas till på huvudbokstransaktionen. | C55: Ska-krav
A56: 3.2.5 | B56: IT-tjänsten ska ha meddelandestöd kopplat till begränsningar av textfält. Dvs begränsningar i antal tecken kopplat till fakturalayouten ska meddelas. | C56: Bör krav | E56: =IF(D56="ja",3,0) -> 0 | F56: =(Jämförelsesumma!$E$6/Jämförelsesumma!$F$6)*E56 -> 0
A57: 3.2.6 | B57: IT-tjänsten ska har funktion för att registrera telefonnummer och e-postadress | C57: Ska-krav
A58: 3.2.7 | B58: IT-tjänsten ska ha funktion för att koppla dokument till kunden. | C58: Ska-krav
A59: 3.2.8 | B59: IT-tjänsten ska ha funktion för att ange tvingande fält, t ex att orgnr/VATnr ska vara ifyllt | C59: Ska-krav
A60: 3.2.9 | B60: IT-tjänsten ska ha funktion för att momsregistreringsnumret ska skrivas på faktura till kund. | C60: Ska-krav
A61: 3.2.10 | B61: IT-tjänsten ska vara flexibelt kring fakturalayouten vid upprättande av fakturaunderlag. ex.vis hantering av längre texter och radbryt. | C61: Ska-krav
A62: 3.2.11 | B62: IT-tjänsten ska ha funktion för att kunna lägga fasta texter på fakturalayouten kopplat till fakturatyp | C62: Ska-krav
A63: 3.2.12 | B63: IT-tjänsten ska ha funktion för olika fakturalayouter beroende på distributionssätt/betalmetod, exempelvis autogiro etc. | C63: Ska-krav
A64: 3.2.13 | B64: IT-tjänsten ska ha funktion för att registrera på kund vilken typ av leveransform de önskar motta sin faktura på. | C64: Ska-krav | G64: ändringen finns i loggen//JP
A65: 3.2.14 | B65: IT-tjänsten ska ha funktion för att koppla kundspecifika villkor mot viss leveransadress eller artikeltyp, t.ex. rabatter, leverans-, betalningsvillkor. | C65: Ska-krav
A66: 3.2.15 | B66: IT-tjänsten ska ha funktion för att gruppera kunder för att sätta särskilda villkor. | C66: Ska-krav
A67: 3.2.16 | B67: IT-tjänsten ska ha funktion för att skapa och lagra mallar för uppläggning av olika slags kunder. | C67: Ska-krav
A68: 3.2.17 | B68: IT-tjänsten ska ha funtion för att läsa in och uppdatera kunduppgifter från externa system. Regler för matchning ska kunna göras på multipla fält. | C68: Ska-krav
A69: 3.2.18 | B69: IT-tjänsten ska ha funktion för att hantera utländska adresser t.ex. avvikande postnummer eller struktur. | C69: Ska-krav
A70: 3.2.19 | B70: IT-tjänsten ska ha funktion för att med inläsning kunna uppdatera anmälningar och avanmälningar för efaktura till internetbank. | C70: Ska-krav
A71: 3.2.20 | B71: IT-tjänsten ska ha funktion att registrera efaktura till internetbank där betalaren är annan än kunden. | C71: Ska-krav
A72: 3.2.21 | B72: IT-Tjänsten ska ha funktion för att manuellt registrera samt ändra uppgifter om kund | C72: Ska-krav
A73: 3.2.22 | B73: I IT-Tjänsten bör det vara möjligt att välja vilka fält som ska vara synliga samt obligatoriska enligt beställarens önskan vid registrering av kund. | C73: Bör-krav | E73: =IF(D73="ja",3,0) -> 0 | F73: =(Jämförelsesumma!$E$6/Jämförelsesumma!$F$6)*E73 -> 0
A74: 3.3 | B74: Inbetalningar och Krav
A75: 3.3.1 | B75: IT-tjänsten ska ha funktion för att hantera elektroniska inbetalningar via bankgiro. | C75: Ska-krav
A76: 3.3.2 | B76: IT-tjänsten ska ha funktion för att hantera elektroniska inbetalningar enligt SEPA-format. | C76: Ska-krav
A77: 3.3.3 | B77: IT-tjänsten ska ha funktion för att hantera elektroniska inbetalningar enligt XML-ISO20022. | C77: Ska-krav
A78: 3.3.4 | B78: IT-tjänsten ska ha stöd för automatisk matchning mot OCR inbetalning oavsett hel- eller delbetalning | C78: Ska-krav
A79: 3.3.5 | B79: IT-tjänsten ska ha stöd för att matcha inbetalning mot vald konteringssträng utifrån avsändare och meddelande på inbetalningsavi. | C79: Ska-krav
A80: 3.3.6 | B80: IT-tjänsten har funktion för att registrera förskottsbetalning mot en order. | C80: Ska-krav
A81: 3.3.7 | B81: IT-tjänsten ska ha funktion för att söka ut och skicka påminnelse på fakturor X antal dagar efter förfallodag. Funktion ska gå att utföra manuellt samt automatiskt utefter uppsatta regler. Det ska vara möjligt att se om en påminnelse skickats. | C81: Ska-krav
A82: 3.3.8 | B82: IT-tjänsten ska ha funktion för påminnelser och kravhantering som separat levereras till beställarens fakturadistributör. | C82: Ska-krav
A83: 3.3.9 | B83: IT-tjänsten ska ha funktion för automatisk ränteberäkning och debitering . | C83: Ska-krav
A84: 3.3.10 | B84: Det ska vara möjligt att granska och redigera fakturaförslag för räntefakturering. | C84: Ska-krav
A85: 3.3.11 | B85: IT-tjänsten ska ha funktion för att undanta räntefakturor och påminnelse för ränteberäkning. | C85: Ska-krav
A86: 3.3.12 | B86: IT-tjänsten ska ha funktion att skicka påminnelse gällande räntefakturor. | C86: Ska-krav
... A98: 3.3.24 | B98: IT-tjänsten ska ha funktion för automatisk bortbokning av inbetalningsdifferens inom definierat beloppsintervall. | C98: Ska-krav
A99: 3.4 | B99: Rapporter
A100: 3.4.1 | B100: IT-tjänsten ska ha stöd för dynamiska rapporter och/eller sökfunktion för förfallna fakturor. | C100: Ska-krav
A101: 3.4.2 | B101: IT-tjänsten ska funktion för att i reskontran kunna se fakturabilden i IT-tjänsten. | C101: Ska-krav
A102: 3.4.3 | B102: I IT-tjänsten ska finnas möjlighet att enkelt göra avstämning av order före fakturering. Denna avstämning ska innehålla uppgifter om bl a kontering, periodiseringsnycklar så att eventuella rättningar kan göras innan fakturering. | C102: Ska-krav
A103: 3.4.4 | B103: IT-tjänsten ska ha funktion för åldersanalys över reskontran (dvs presentation över åldersfördelningen av fordringarna). | C103: Ska-krav
A104: 3.4.5 | B104: IT-tjänsten ska ha funktion för att presentera statistik såsom t.ex. historik, omsättning per kund, antal fakturor per kund, antal krav, genomsnittlig kredittid. | C104: Ska-krav
A105: 3.4.6 | B105: IT-tjänsten ska ha stöd för export till andra icke-ändringsbara format som exempelvis PDF. | C105: Ska-krav
A106: 3.4.7 | B106: IT-tjänsten ska ha funktion för att skapa fellista vid ej matchade inbetalningar | C106: Ska-krav
A107: 3.4.8 | B107: Det ska vara möjligt att söka fram fakturor för respektive status | C107: Ska-krav
A108: 3.4.9 | B108: Systemet bör ha funktion för att publicera "mina sidor" för kunder där de kan se obetalda/betalda fakturor | C108: Bör-krav | E108: =IF(D108="ja",5,0) -> 0 | F108: =(Jämförelsesumma!$E$6/Jämförelsesumma!$F$6)*E108 -> 0
B109: Summa Börkravspoäng: | E109: =SUM(E6:E108) -> 0

Sheet 7. Logistik
A1: 7 | B1: Logistik | C1: Beskrivning efterfrågas | D1: Ingår | E1: Utv | H1: Utfall
A2: Nr | B2: Område/funktion | D2: J/N | E2: J/N | F2: Kommentar av leverantör
A3: 7.1 | B3: Generella krav
A4: 7.1.1 | B4: Systemet har funktion för att kunna lägga internorder från ett bolag till ett annat. -Beskriv systemets funktioner för internhandel. | C4: x
A5: 7.1.2 | B5: Systemet har funktion för att skapa extern inköpsorder baserad på internorder
A6: 7.1.3 | B6: Systemet har funktion för att lagra information om leverantörer är prioriterad eller ej
A7: 7.1.4 | B7: Systemet har funktion för att föreslå prioriterad leverantör för inköpsorder
A8: 7.1.5 | B8: Systemet har funktion för att ta emot orderbekräftelse från leverantör elektroniskt och därmed ändra status på inköpsorder
A9: 7.1.6 | B9: Systemet har funktion för att kunna lägga orderbekräftelse på internorder
A10: 7.1.7 | B10: Systemet har funktion för dokumenthantering av packlistor, leveransbesked och andra leveransdokument. -Beskriv hanteringen av leveransdokument och leveransbesked till kund. | C10: x
A11: 7.1.8 | B11: Systemet har funktion för att få transparens från en inköpsorder i Kina-bolaget till en kundorder i det Svenska-bolaget (dvs. systemet knyter ihop kundorderna med inköpsordern via en inter-company order och kan uppdatera statusändringar på inköpsordern till kundordern). -Besrkiv hur detta löses av systemet. | C11: x
A12: 7.2 | B12: Lagerstyrning
A13: 7.2.1 | B13: Systemet har funktion för att ha negativa lagersaldon, dvs. att kunna utleverera fast ännu inte inleverans i systemet är utförd. | H13: =+D13*#REF! -> #REF!
A14: 7.2.2 | B14: Systemet har funktion för att hantera olika typer av kostnad sålda varor såsom ”äkta” FIFO, standardkostnad, genomsnittspris samt återanskaffningspris (senaste inköp). -Beskriv hur systemet hanterar frakt, pålägg, tull etc. | C14: x | H14: =+D14*#REF! -> #REF!
A15: 7.2.3 | B15: Systemet har funktion för att sätta kostpris för en artikel baserat på inköpspris + faktisk transportkostnad. | H15: =+D15*#REF! -> #REF!
A16: 7.2.4 | B16: Systemet har funktion för att visa kommande dags planerade inleveranser.
A17: 7.2.5 | B17: Systemet har funktion för flera lager.
A18: 7.2.6 | B18: Systemet har funktion för flera lagerplatser per lager.
A19: 7.2.7 | B19: Systemet har funktion för flera hyllr per lagerplatser.
A20: 7.2 | B20: In- och Utleveranser | H20: =+D20*#REF! -> #REF!
A21: 7.3.1 | B21: Systemet har funktion för att generera en lista varje morgon som visar alla inköp som skall komma in "idag", kunna se vilka artiklar som det är orderstock på och hantera dessa först samt se olika handpåläggningskrav, förbereda frakt kolla kreditvärdighet, meddela sälj/kund om att gods är på väg in, fråga om delleverans etc.
A22: 7.3.2 | B22: Systemet har funktion för att inleverera artiklar mot inköpsorder.
A23: 7.3.3 | B23: Systemet har funktion för att visa alla rader på inköpsordern, kan göra urval samt ändra antal eller boka in hela inköpet.
A24: 7.3.4 | B24: Systemet har funktion för att kunna stämma av inköpsrader, leverantörsdata och få all nödvändig info presenterad av artiklarna som behöver verifieras/godkännas för inbokning, tex rätt antal, rätt innehåll etc.
A25: 7.3.5 | B25: Systemet har funktion för att om någon data saknas vid inbokning skall denna info skickas via epost eller skrivas ut, tex art 1 saknar vikt, art 2 saknar statnr, meddela leverantör (välja vem som skall kontaktas).
A26: 7.3.6 | B26: Systemet har funktion för att datumstämpla artiklar vid inregistrering i lager, när man omdisponerar från olika lager så får man som förslag att hämta från äldsta lagret först.
A27: 7.3.7 | B27: Systemet har funktion för att notifiera om att en artikel blivit inlevererad (t ex till säljare när en produkt är tillgänglig för leverans).
A28: 7.3.8 | B28: Systemet har funktion för att bevaka kommande utleveranser.
A29: 7.3.9 | B29: Systemet har funktion för restorder. | H29: =+D29*#REF! -> #REF!
A30: 7.3.10 | B30: Systemet har funktion för övervakning av order, så att inga ligger obehandlade i systemet. | H30: =+D30*#REF! -> #REF!
A31: 7.3.11 | B31: Systemet har funktion för att sända leveransavisering till kunden i samband med leveransen. | H31: =+D31*#REF! -> #REF!
A32: 7.3.12 | B32: Systemet har funktion för att skriva ut packsedel via enstaka urval eller alla inneliggande leveransklara order. | H32: =+D32*#REF! -> #REF!
A33: 7.3.13 | B33: Systemet har en funktion som kan hantera kundens adressuppgifter och per auto fylla i dessa på adresslapp för olika fraktleverantörer
A34: 7.3.14 | B34: Systemet har funktion för att registrera serienummer på artiklar vid plockning/utleverans.
A35: 7.4 | B35: Rapporter | H35: =+D35*#REF! -> #REF!
A36: 7.4.1 | B36: Systemet har rapport för artiklar per lagerplats.
A37: 7.4.2 | B37: Systemet har rapport för försenade kundorder, alla kundorder som behöver kontaktas.
A38: 7.4.3 | B38: Systemet har rapport för artiklar med negativt saldo.
A39: 7.4.4 | B39: Systemet har rapport för inventerade artiklar, datum, saldo, korrigering
A40: 7.4.5 | B40: Systemet har rapport för lagervärde FIFO, där man kan göra urval och/eller exkludera artikel/artikeltyp

Sheet 8. Försäljning
A1: 9 | B1: Försäljning | C1: Beskrivning efterfrågas | D1: Ingår | E1: Utv | H1: Utfall
A2: Nr | B2: Område/funktion | D2: J/N | E2: J/N | F2: Kommentar av leverantör
A3: 9.1 | B3: Generella krav
A4: 9.1.1 | B4: Systemet har funktion för att sätta och följa upp säljbudget för respektive säljare och produktkategori. | H4: =+D4*#REF! -> #REF!
A5: 9.1.2 | B5: Systemet har funktion för att arbeta med säljprognoser för säljare, kund, kundgrupp, artikel och artikelgrupp. Ska även inkludera historik, dvs jämförelse/förändring mot tidigare lämnade prognoser, samt utfall vs prognos | C5: x | H5: =+D5*#REF! -> #REF!
A6: 9.1.3 | B6: Systemet har funktion för att koppla mail/dokument (MS-Office/PDF) till kunder och kundorder. | H6: =+D6*#REF! -> #REF!
A7: 9.1.4 | B7: Systemet har funktion för att flytta kontakter, aktiviteter dokument & historik från en säljare till annan vid t.ex. byten av ansvarsområden eller när säljare slutar. | H7: =+D7*#REF! -> #REF!
A8: 9.1.5 | B8: Systemet har funktion för att lägga in speciella överenskommelser på kunden som visas nästa gång man registrerar in en beställning från kunden (t. ex. fraktfri leverans vid nästa beställning). | H8: =+D8*#REF! -> #REF!
A9: 9.1.6 | B9: Systemet har stöd för att i en sammanställd kundbild visa all relevant information om kunden (t.ex. orderhistorik, offerter, ärende etc.), samt även kunna visa en sammanställd bild per produkt. T ex vilka kunder har köpt, vilka volymer, till vilket pris, med vilken produkt-marginal, per artikel o artikelfamilj, finns verktyg, vem är leverantör etc (se även pkt 9.8.15 nedan)
A10: 9.2 | B10: Säljaktiviteter | H10: =+D10*#REF! -> #REF!
A11: 9.2.1 | B11: Systemet har funktion för att löpande skriva noteringar (föra journal) om kunden (tex i samband med telefonkontakt eller korrespondens) vilka kan lagras sorterat per datum och användare.
A12: 9.2.2 | B12: Systemet har funktion för att registrera säljaktiviteter och noteringar per kund (planerade möten, telefonsamtal odyl). | H12: =+D12*#REF! -> #REF!
A13: 9.2.3 | B13: Systemet har funktion för att till planerade aktiviteter generera påminnelser samt integrera dessa med användarens kalender i Outlook/Office 365. | H13: =+D13*#REF! -> #REF!
A14: 9.2.4 | B14: Systemet har funktion för att registrera potentiella kunder (leads, prospects) med begränsad information. | H14: =+D14*#REF! -> #REF!
A15: 9.2.5 | B15: Systemet har rapport för att visa aktivitetsuppföljning på säljare (t.ex. nykundsamtal / bokade möten). | H15: =+D15*#REF! -> #REF!
A16: 9.2.6 | B16: Systemet har stöd för skapande av offerter (med en eller flera artiklar) med tidsbestämda giltighetstider
A17: 9.2.7 | B17: Systemet har stöd för mall-hantering vid offert med förifylld information t ex default payment term, warranty, validity etc
A18: 9.2.8 | B18: Systemet har funktion för att ta med offerter för specifika artiklar i inköpsförslag/prognoser.
A19: 9.3 | B19: Kundorder | H19: =+D19*#REF! -> #REF!
A20: 9.3.1 | B20: Systemet har funktion för att konfigurera vilka fält och uppgifter som skall vara obligatoriska att fylla i vid orderregistrering. | H20: =+D20*#REF! -> #REF!
A21: 9.3.2 | B21: Systemet har funktion för att beräkna ett första möjligt leveransdatum baserat på artiklars tillgänglighet i lager, planerade inleveranser samt registrerade ledtider. | H21: =+D21*#REF! -> #REF!
A22: 9.3.3 | B22: Systemet har funktion för att läsa in olika typer av kundbeställningar elektroniskt. -Beskriv vilka lösningar och format ni erbjuder för detta. | C22: x | H22: =+D22*#REF! -> #REF!
A23: 9.3.4 | B23: Systemet har funktion för att överföra offert till order. | H23: =+D23*#REF! -> #REF!
A24: 9.3.5 | B24: Systemet har ett fält för beräknad leveranstid. | H24: =+D24*#REF! -> #REF!
A25: 9.3.6 | B25: Systemet skall även kunna hantera specifika projektorders från order-inköp-leverans. | H25: =+D25*#REF! -> #REF!
A26: 9.4 | B26: Orderbekräftelse | H26: =+D26*#REF! -> #REF!
A27: 9.4.1 | B27: Systemet har funktion för att skapa och sända en orderbekräftelse till kunden elektroniskt. | H27: =+D27*#REF! -> #REF!
A28: 9.4.2 | B28: Systemet har stöd för att automatiskt sända uppdaterat leveransbesked till kund när inleveranstid förändras för beställd artikel. | H28: =+D28*#REF! -> #REF!
A29: 9.5 | B29: Prissättning | H29: =+D29*#REF! -> #REF!
A30: 9.5.1 | B30: Systemet har funktion för att vid orderregistrering överstyra den prissättning och leveranstid som systemet föreslår. | H30: =+D30*#REF! -> #REF!
A31: 9.5.2 | B31: Systemet har funktion för kundunika prislistor. | H31: =+D31*#REF! -> #REF!
A32: 9.5.3 | B32: Systemet har funktion för att sätta giltighetstider (from-tom datum) på prislistorna. | H32: =+D32*#REF! -> #REF!
A33: 9.5.4 | B33: Systemet har funktion för volymbaserade och stafflade försäljningsrabatter. | H33: =+D33*#REF! -> #REF!
A34: 9.5.5 | B34: Systemet har funktion för att styra försäljningspris baserat på prislisor för kund och kundkategori med rabattter på artikel, artikelkategori och stafflat baserat på ordervolym. | H34: =+D34*#REF! -> #REF!
... A39: 9.6.3 | B39: Systemet har funktion för att registrera in beskrivning av felet, produkt, orsak, kontaktuppgifter, ordernummer samt en prioritetsnivåkod. | H39: =+D39*#REF! -> #REF!
A40: 9.6.4 | B40: Systemet har funktion för serienummerhantering som underlag för RMA:er hantering
A41: 9.6.5 | B41: Systemet har funktion för registrering av status och åtgärd på RMA:er | H41: =+D41*#REF! -> #REF!
A42: 9.7 | B42: Fakturering | H42: =+D42*#REF! -> #REF!
A43: 9.8.1 | B43: Systemet har funktion för att automatiskt skapa fakturaunderlag för utlevererade ordrar. | H43: =+D43*#REF! -> #REF!
A44: 9.8.2 | B44: Systemet har funktion för att komplettera och justera fakturaunderlaget innan fakturering. | H44: =+D44*#REF! -> #REF!
A45: 9.8.3 | B45: Systemet har funktion för periodisering direkt vid faktureringstillfället. | H45: =+D45*#REF! -> #REF!
A46: 9.8.4 | B46: Systemet har funktion för automatkontering av intäkter/moms.
A47: 9.8.5 | B47: Systemet har funktion för att frisläppa respektive orderrad för fakturering.
A48: 9.8.6 | B48: Systemet har funktion för att skicka elektronisk faktura i pdf via epost. | H48: =+D48*#REF! -> #REF!
A49: 9.8.7 | B49: Systemet har funktion för att använda olika fakturalayouter med olika detaljeringsgrad (faktura enbart med totalsumma, faktura med detaljer per respektive strukturdel i produktstrukturen). | H49: =+D49*#REF! -> #REF!
A50: 9.8.8 | B50: Systemet har funktion för att arbeta med olika layouter av fakturablanketter - kopplat till olika kundgrupper/kundtyper och proformafakturor (till tullen). | H50: =+D50*#REF! -> #REF!
A51: 9.8.9 | B51: Systemet har funktion för att styras per kund och per kundorder vilken fakturatyp/fakturamall som används. | H51: =+D51*#REF! -> #REF!
A52: 9.8.10 | B52: Systemet har funktion för att visa faktura på skärm (print preview) samt skapa i pdf-format. | H52: =+D52*#REF! -> #REF!
A53: 9.8.11 | B53: Systemet har funktion för att bakdatera faktura | H53: =+D53*#REF! -> #REF!
A54: 9.8.12 | B54: Systemet har funktion att vid godkänt returärende hämtas krediteringsuppgifter från RMA. | H54: =+D54*#REF! -> #REF!
A55: 9.8.13 | B55: Systemet har funktion för att fakturera både i förskott och efterskott. | H55: =+D55*#REF! -> #REF!
A56: 9.8.14 | B56: Systemet har rapport för uteliggande offerter och ordrar per kund. | H56: =+D56*#REF! -> #REF!
A57: 9.8.15 | B57: Systemet har rapport för försäljningsstatistik över artiklar sålda per kund och till vilken prisnivå.

Sheet 4. Leverantörsreskontra
A1: ='1. Generellt'!A1 -> Ekonomisystem, UPP-2025/047 | C1: Anbudsgivare: | D1: =Information!D1 -> 0
A3: 4 | B3: Leverantörsreskontra | C3: Typ av krav | D3: Uppfylls bör-kravet? | E3: Bör-kravet vikt/poäng | F3: Avdrag för uppfyllda bör-krav
A4: Nr | B4: Område/funktion
A5: 4.1 | B5: Allmänt
A6: 4.1.1 | B6: IT-tjänsten ska ha funktion för att periodisera leverantörsfakturor via intergration eller vid manuell registrering. | C6: Ska-krav
A7: 4.1.2 | B7: IT-tjänsten ska registrera leverantörsfakturor som leverantörsskulder i huvudboken och reskontran vid ankomst | C7: Ska-krav
A8: 4.1.3 | B8: Det ska finnas möjlighet i IT-tjänsten att sätta regler för kontering | C8: Ska-krav
A9: 4.1.4 | B9: Det ska vara möjligt att justera momsbelopp vi manuell bokning | C9: Ska-krav
A10: 4.1.5 | B10: IT-tjänsten ska ha funktion för att ändra förfallodatum på en definitivbokad faktura. | C10: Ska-krav
A11: 4.1.6 | B11: IT-tjänsten ska kunna särskilja bokföring för intern handel (kommunintern och förvaltningsintern) där hanteringen sker i Beställarens fakturahanteringsystem/e-handelssystem . | C11: Ska-krav
A12: 4.1.7 | B12: IT-Tjänsten ska ha funktion för manuell ändring av förfallodatum och betalningsmetod på en definitivbokförd faktura | C12: Ska-krav
A13: 4.1.8 | B13: IT-tjänsten ska ha funktion för att pausa/parkera en faktura innan utbetalning. D.v.s när den är defintivbokad. | C13: Ska-krav
A14: 4.1.9 | B14: IT-tjänsten ska ha funktion för att varna för registrering av dubbletter. | C14: Ska-krav
A15: 4.2 | B15: Betalning
A16: 4.2.1 | B16: IT-tjänsten ska stödja tvåhandsprincipen för betalningsuppdrag. | C16: Ska-krav
A17: 4.2.2 | B17: IT-tjänsten ska kunna skapa flera betalningsförslag kopplat till olika typer av betalningar. | C17: Ska-krav
A18: 4.2.3 | B18: IT-tjänsten ska ha funktion för att elektroniskt läsa in bekräftelse av utförda betalningar med automatmatchning. | C18: Ska-krav
A19: 4.2.4 | B19: IT-tjänsten ska ha funktion för betalning i annan valuta än SEK med automatisk beräkning av kursvinst/kursförlust mellan faktura & betalning samt bankavgifter | C19: Ska-krav
A20: 4.2.5 | B20: IT-tjänsten ska ha funktion för att återaktivera en faktura som blivit avvisad av bank. | C20: Ska-krav
A21: 4.2.6 | B21: IT-tjänsten ska ha funktion för att skapa en fil på betalningsförslag som kan skickas för kontroll av innehållet till beställarens valda leverantör. | C21: Ska-krav
A22: 4.3 | B22: Rapporter
A23: 4.3.1 | B23: Det ska vara möjligt att söka fram fakturor för respektive status | C23: Ska-krav
A24: 4.3.2 | B24: IT-tjänsten ska kunna skapa rapport över obetalda fakturor (åldersanalys av leverantörsreskontra). | C24: Ska-krav
A25: 4.3.3 | B25: IT-tjänsten ska kunna skapa rapport med betalningsprognoser. | C25: Ska-krav
A26: 4.3.5 | B26: IT-tjänsten ska ha funktion för att skapa rapport för samtliga fakturor kopplat till en leverantör. | C26: Ska-krav
A27: 4.5 | B27: Leverantörsregister
A28: 4.5.1 | B28: IT-tjänsten ska ha funktion för att läsa in och uppdatera leverantörsuppgifter från externa system. Regler för matchning ska kunna göras på multipla fält. | C28: Ska-krav
A29: 4.5.2 | B29: IT-tjänsten ska ha funktion för att via Excel läsa in och uppdatera leverantörsuppgifter. Regler för matchning ska kunna göras på multipla fält. | C29: Ska-krav
A30: 4.5.3 | B30: IT-tjänsten ska ha funktion för att kunna lägga upp nya leverantörer och uppdatera befintliga leverantörer manuellt. | C30: Ska-krav
A31: 4.5.4 | B31: IT-tjänsten ska ha funktion för att särskilja leverantörsgrupper. | C31: Ska-krav
A32: 4.5.5 | B32: IT-tjänsten ska ha funktion för att registrera koncernkod på leverantör(koncern/dotterföretag) vilken styr avvikande lev.skuldskonto. | C32: Ska-krav
A33: 4.5.6 | B33: IT-tjänsten ska ha funktion för att registrera bankuppgifter till utländska leverantörer, så som IBAN-kontonummer, BIC/SWIFT, amerikansk standard. | C33: Ska-krav
A34: 4.5.7 | B34: IT-tjänsten ska ha stöd för att signalera/rapportera vid nyupplagd leverantör eller ändring i leverantörsregister. | C34: Ska-krav
A35: 4.5.8 | B35: IT-tjänsten ska ge möjlighet att registrera flera betaluppgifter på samma leverantör, t ex uppgifter om factoringbolag. | C35: Ska-krav
A36: 4.5.9 | B36: IT-tjänsten ska ge möjlighet att resistrera betaluppgifter på leverantören. Som minst Plusgiro, Bankgiro, Bankkontonummer och utbetalningskort. | C36: Ska-krav
A37: 4.5.10 | B37: IT-tjänsten ska ha funktion för koppla dokument till leverantören och leverantörsfaktura | C37: Ska-krav | I37: nej
A38: 4.5.11 | B38: IT-tjänsten bör ha funktion för att från Excel importera och skapa leverantörsfakturor och betalningar. | C38: Bör krav | E38: =IF(D38="ja", 3, 0) -> 0 | F38: =(Jämförelsesumma!$E$6/Jämförelsesumma!$F$6)*E38 -> 0
A39: 4.5.12 | B39: IT-tjänsten bör ha funktion att förenkla leverantörupplägg genom att hämta bolagsinformation (som minst organisationsnummer, betalningsuppgifter, f-skatt, bluff.) från t ex. Inyett eller annan aktör. | C39: Bör krav | E39: =IF(D39="ja", 3, 0) -> 0 | F39: =(Jämförelsesumma!$E$6/Jämförelsesumma!$F$6)*E39 -> 0 | I39: ja
D40: Summa Börkravspoäng: | E40: =SUM(E6:E39) -> 0

Sheet 5. Anläggningsregister
A1: ='1. Generellt'!A1 -> Ekonomisystem, UPP-2025/047 | C1: Anbudsgivare: | D1: =Information!D1 -> 0
A3: 5 | B3: Anläggningsregister | C3: Typ av krav
A4: Nr | B4: Område/funktion
A5: 5.1 | B5: Allmänt
A6: 5.1.1 | B6: IT-tjänsten ska ha funktion för att hantera anläggningar och göra avskrivningar på dessa med linjär avskrivning över valfri tidsperiod. | C6: Ska-krav
A7: 5.1.2 | B7: Det ska vara möjligt att ha valfria avskrivningstider per anläggningsgrupp. | C7: Ska-krav
A8: 5.1.3 | B8: IT-tjänsten ska ha funktion för att skriva av till registrerat restvärde. | C8: Ska-krav
A9: 5.1.4 | B9: IT-tjänsten ska ha funktion för att registrera in och följa upp leasade inventarier (t.ex. fordon). | C9: Ska-krav
A10: 5.1.5 | B10: IT-tjänsten ska ha funktion för att beräkna och bokföra skattemässig avskrivning och avskrivning enligt ekonomisk livslängd. | C10: Ska-krav
A11: 5.1.6 | B11: IT-tjänsten ska ha funktion för att göra avyttringar upp/nedskrivningar i IT-tjänsten och automatiskt få detta konterat. | C11: Ska-krav
A12: 5.1.7 | B12: IT-tjänsten ska ha stöd för komponentavskrivning. | C12: Ska-krav
A13: 5.1.8 | B13: IT-tjänsten ska hantera beräkningar av framtida avskrivningar (estimat för budget arbete) på valfri organisatorisk nivå. | C13: Ska-krav
A14: 5.1.9 | B14: IT-tjänsten ska ha funktion för att justera avstämningskonton i anläggningsreskontran om felaktiga differenser uppstår mellan reskontra och huvudbok. | C14: Ska-krav
A15: 5.1.10 | B15: IT-tjänsten ska ha möjlighet att till en anläggning ange värden på samtliga koddelar/kodsträngen och vid behov organisatorisk tillhörighet. | C15: Ska-krav
A16: 5.1.11 | B16: IT-Tjänsten ska ha funktion för att göra avstämningar mellan huvudbok och anläggningsregistret | C16: Ska-krav
A17: 5.1.12 | B17: IT-Tjänsten ska ha funktion för att automatiskt beräkna internränta.
A18: 5.2 | B18: Registrera anläggning
A19: 5.2.1 | B19: Anläggningsregister ska vara integrerad med leverantörsreskontran. Detta möjliggör att nyregistrera en anläggning vid registrering av leverantörsfaktura. | C19: Ska-krav
A20: 5.2.2 | B20: IT-tjänsten ska kunna hantera bokningar via manuella bokföringsordrar på anskaffningsreskontrans tillgångskonton och generera post i anläggningsregistret. | C20: Ska-krav
A21: 5.2.3 | B21: Ändringar i anläggningsregistret avseende koddelar/kontosträng ska generera automatiskt huvudbokstransaktioner. T ex byte av kostnadsställe. | C21: Ska-krav
A22: 5.2.4 | B22: I basuppgifter ska det finnas ett eller flera "fritext"-fält för varje inventarie eller anläggning. | C22: Ska-krav
A23: 5.2.5 | B23: IT-tjänsten ska tillhandahålla spårbarhet så som ange anläggnings geografiska läge och vem som innehar den. Möjlighet att enkelt ändra/uppdatera. | C23: Ska-krav
A24: 5.2.6 | B24: IT-tjänsten ska ha funktion för att ange olika typer av anläggningar. | C24: Ska-krav
A25: 5.2.7 | B25: Ett färdigställt projekt (t.ex. ombyggnad av kontor) ska kunna överföras till anläggningsregistret. | C25: Ska-krav
A26: 5.2.8 | B26: IT-tjänsten ska tillhandahålla funktion för att registrera in anläggningar utan värde. | C26: Ska-krav
A27: 5.2.9 | B27: Det ska gå att efterregistrera anläggningar. Det ska vara möjligt att bakdatera de ackumelerade avskrivningarna bokförda i öppen period. | C27: Ska-krav
A28: 5.2.10 | B28: IT-tjänsten ska ha stöd för att registrera och hantera investeringsbidrag kopplat till anläggningstillgångar | C28: Ska-krav
A29: 5.3 | B29: Rapporter
A30: 5.3.1 | B30: IT-tjänsten ska ha utfallsdokument/rapport på räkenskapsenliga och skattemässiga avskrivningar av inventarier och anläggningstillgångar samt olika avskrivningsplaner. | C30: Ska-krav
A31: 5.3.2 | B31: Det ska gå att se återstående anläggningars värde och avskrivningar årsvis framåt. | C31: Ska-krav
A32: 5.3.3 | B32: IT-tjänsten ska tillhandahålla fullständig standardrapport för investeringar, avskrivningar och restvärde per period och anläggningsid. Rapporten ska gå att summeras på ovan nämnda värden. | C32: Ska-krav
A33: 5.3.4 | B33: IT-tjänsten ska kunna tillhandahålla rapporter över anläggningar per konto, ansvar och typ samt valfria kombinationer och urval av dessa. | C33: Ska-krav

Sheet 6. Projekt
A1: ='1. Generellt'!A1 -> Ekonomisystem, UPP-2025/047 | C1: Anbudsgivare: | D1: =Information!D1 -> 0
A3: 6 | B3: Projekt
A4: Nr | B4: Område/funktion | C4: Typ av krav
A5: 6.1 | B5: Projektregister
A6: 6.1.1 | B6: Det ska vara möjligt att skapa projekt i IT-tjänsten. | C6: Ska-krav
A7: 6.1.2 | B7: Projekt ska kunna delas upp i underprojekt. | C7: Ska-krav
A8: 6.1.3 | B8: I IT-tjänsten ska det vara möjligt men inte tvingande att lägga upp budget per projekt. | C8: Ska-krav
A9: 6.1.4 | B9: Projekt ska kunna ha flera olika status, t.ex. budget, pågående och avslutat. | C9: Ska-krav
A10: 6.1.5 | B10: Det ska finnas möjligheter att använda mallar med uppsatta parametrar som man kopiera när man lägger upp nya projekt. | C10: Ska-krav
A11: 6.1.6 | B11: Projekt och dess delar ska antingen kunna balansföras (för senare aktivering) eller resultatföras. | C11: Ska-krav
A12: 6.2 | B12: Avslut av projekt
A13: 6.2.1 | B13: Funktionalitet för att kunna stänga delar av och hela projekt samt aktiviteter ska finnas. | C13: Ska-krav
A14: 6.2.2 | B14: Det ska vara möjligt för ansvariga att återöppna stängda aktiviteter och projekt för ytterligare rapportering. | C14: Ska-krav
A15: 6.3 | B15: Rapporter
A16: 6.3.2 | B16: Det ska vara möjligt att löpande följa upp upparbetad kostnad/intäkt per projekt och underprojekt. | C16: Ska-krav

Sheet 7. Införande och förvaltning
A1: ='1. Generellt'!A1 -> Ekonomisystem, UPP-2025/047 | C1: Anbudsgivare: | D1: =Information!D1 -> 0
A3: 7 | B3: Införande och förvaltning | C3: Typ av krav | D3: Uppfylls bör-kravet? | E3: Bör-kravets vikt/ poäng eller högst avdrag | F3: Avdrag för uppfyllda bör-krav
A4: Nr | B4: Område/funktion
A5: 7.1 | B5: Införandet av IT-tjänsten
A6: 7.1.1 | B6: Leverantören ska tillhandahålla de tjänster som fordras vid införandet av IT-tjänsten, såsom projektledning för leverantörens åtagande, initial utbildning, migrering, installation och driftsättning, implementeringstjänster samt integration med befintliga system. | C6: Ska-krav
A7: 7.1.2 | B7: Vid införande av IT-tjänsten ska Leverantören tillsammans med Beställaren konfigurera, parametersätta och ställa in tjänsten i en iterativ process enligt Beställarens behov. | C7: Ska-krav
A8: 7.1.3 | B8: Båda parterna ska ha utsedda projektledare som tillsammans tar fram en projektplan och leder införandet av IT-tjänsten. | C8: Ska-krav
A9: 7.1.4 | B9: Leverantören ska under införandet tillsätta dokumenterade erfarna konsulter med god kännedom inom respektive komponent i IT-tjänsten och hur dessa på bästa sätt anpassas till kundens behov. Beställaren ska få godkänna konsulterna via granskning av deras CVn, vid uppdragsstart och även vid eventuellt byte av konsulter. Se även avsnitt "Leverantörens personal" i Huvudavtalet. | C9: Ska-krav
A10: 7.1.5 | B10: Leverantören ska för införande av IT-tjänsten tillsätta en dokumenterad erfaren projektledare med erfarenhet av att införa samma IT-tjänst hos en motsvarande kund. Beställaren ska få godkänna projektledaren via granskning av dennes CV. | C10: Ska-krav
A11: 7.1.6 | B11: Leverantörens projektledare ska under hela införandeprojektet driva Leverantörens införandeaktiviteter samt rapportera till Beställarens projektledare för införandet. | C11: Ska-krav
A12: 7.1.7 | B12: Parterna ska utse en projektgrupp snarast efter det att Avtal ingåtts. Projektgruppen ska bestå av de representanter som respektive Part utsett och ska ha befogenhet att företräda Parten inom ramen för projektgruppens arbete. | C12: Ska-krav
A13: 7.1.8 | B13: Direkt efter avtalstecknande ska ett första projektmöte genomföras, där en gemensam plan för införande av IT-tjänsten ska göras tillsammans med Beställaren. Leverantören ska kunna utgå från det förslag på införandeplan som ingår i anbudet. Leverantören ska kunna delta i ett sådant möte inom 2 (två) veckor från avtalsstart (avtalsstart framgår i Huvudavtalet). | C13: Ska-krav
A14: 7.1.9 | B14: Slutgiltig projektplan ska godkännas skriftligt av båda parter innan införandet kan påbörjas. | C14: Ska-krav
A15: 7.1.10 | B15: Projektledaren hos Leverantören ska vid införandet av IT-tjänsten utgöra en single point of kontakt för Beställaren. | C15: Ska-krav
A16: 7.1.11 | B16: Leverantörens utsedda projektledare och tekniska konsulter ska vara tillgängliga under hela införandeprojektet, detta gäller även om införandet försenas. | C16: Ska-krav
A17: 7.1.12 | B17: Leverantören ska ansvara för att leveranstester utförs på ett grundligt sätt och åtgärdar eventuella fel innan Beställarens acceptanstester tar vid. | C17: Ska-krav
... A24: 7.1.19 | B24: Leverantören ska vid införande kunna utgå från till sitt anbud bifogat förslag på införandeplan (framtaget i enlighet med Beställarens förutsättningar och krav i upphandlingsdokument), enligt Bilaga 14 Förslag på införandeplan. | C24: Ska-krav
A25: 7.2 | B25: Utbildning
A26: 7.2.1 | B26: I samband med Införandeprojektet ska Leverantören genomföra utbildningar både riktade till alla användare men även anpassade till de olika funktionerna (rollerna) och efter de processe/moduler som finns i IT-tjänsten med syftet att säkerställa att personalen kan använda IT-tjänsten. Generella utbildningen som riktar sig till alla användare ska beröra ca 70 personer. De specifika rollerna är exempelvis: Systemadministratör, Ekonom, Controller, Ekonomiassistent samt övriga Handläggare. Kostnaden för dessa utbildningar ska ingå i kostnaden för Införandeprojektet. | C26: Ska-krav
A27: 7.2.2 | B27: Leverantören ska tillhandahålla utbildningsmaterial. Utbildningsmaterial ska vara på svenska. Beställare ska ha rätt att använda utbildningsmaterialet för internutbildning inom organisationen, exempelvis vid nyanställningar. | C27: Ska-krav
A28: 7.2.3 | B28: Utbildningen ska, om inget annat överenskommes mellan Parterna, ske i Huddinge kommuns lokaler eller Digitalt | C28: Ska-krav | H28: ja
A29: 7.2.4 | B29: Leverantören bör kunna tillhandahålla en e-utbildning till Användare under avtalstiden. | C29: Bör krav | E29: =IF(D29="ja",2,0) -> 0 | F29: =(Jämförelsesumma!$E$6/Jämförelsesumma!$F$6)*E29 -> 0 | H29: nej
A30: 7.2.5 | B30: Vid större förändringar efter det att IT-tjänsten tagits i bruk ska utbildning ske för berörd personal. | C30: Ska-krav
A31: 7.2.6 | B31: I införandet ska Leverantören tillhandahålla en kundspecifik utbildningsmiljö. Utbildningsmiljön ska vara så identisk utifrån funktionalitet med den planerade produktionsmiljön som är praktiskt möjligt. | C31: Ska-krav
A32: 7.2.7 | B32: Leverantören ska fortlöpande erbjuda utbildning i IT-tjänsten för hos Beställaren nya användare. Kostnad för detta debiteras enligt p.4.1-4.2 flik "Priser" Leverantören ska kunna tillhandahålla utbildningar enligt beskrivet utbildningsutbud som lämnats i samband med anbudet. | C32: Ska-krav
A33: 7.3 | B33: Samverkan och förvaltning
A34: 7.3.1 | B34: Samverkan ska ske i enlighet med vad som framgår i Bilaga 4 - Samverkan och ändringshantering. Leverantör ska gemensamt med Beställaren ta fram och etablera samverkansorganisationen. Samverkansorganisationen och de personer som verkar i olika roller i den ska dokumenteras tydligt. | C34: Ska-krav
A35: 7.3.2 | B35: Anbudsgivaren ska i samverkan med kommunen aktivt delta i förvaltning av IT-tjänsten samt i arbetet att förbättra och utveckla IT-tjänsten. | C35: Ska-krav
A36: 7.3.3 | B36: Anbudsgivaren ska fortlöpande samla in kundens synpunkter och behov för vidareutveckling av IT-tjänsten. | C36: Ska-krav
A37: 7.3.4 | B37: Anbudsgivaren ska presentera sin hantering av framtida utveckling av IT-tjänsten | C37: Ska-krav
A38: 7.3.5 | B38: En aktiv kundgrupp ska finnas med återkommande utvecklingsträffar (minst en gång per år). | C38: Ska-krav
A39: 7.4 | B39: Kundansvarig/konsulttjänter
A40: 7.4.1 | B40: Leverantören ska tillhandahålla en kundansvarig som ska vara huvudansvarig för tjänsternas utförande gentemot Beställaren. | C40: Ska-krav
A41: 7.4.2 | B41: Kundansvarig ska ha goda kunskaper om och erfarenhet av IT-tjänsten som Leverantören tillhandahåller inom ramen för avtalet. Kundansvarig ska ha fullgod kännedom om Leverantörens aktuella processer, tjänster och konsulter. | C41: Ska-krav
A42: 7.4.3 | B42: Kundansvarig ska normalt vara tillgänglig kontorstid, vardagar, och ha en återkopplingstid på max 2 arbetsdagar. Ansvaret får överlämnas till annan hos leverantören anställd med likvärdig kompetens vid frånvaro. | C42: Ska-krav
A43: 7.4.4 | B43: Kundansvarig ska ha tidigare erfarenhet av rollen som kundansvarig. | C43: Ska-krav
A44: 7.4.5 | B44: Kundansvarig ska kunna bytas ut på Beställarens begäran | C44: Ska-krav
A45: 7.4.6 | B45: Leverantören ska kunna tillhandahålla tekniska konsulttjänster, såsom utveckling och anpassning, av IT-tjänsten under avtalstiden. | C45: Ska-krav
A46: 7.4.7 | B46: Leverantören ska i största möjliga mån tillhandahålla en till Beställaren dedikerad teknisk konsult som är väl insatt i Beställarens uppsättning av IT-tjänsten. Om konsulten måste bytas p.g.a. sakliga skäl (vilket Beställaren måste godkänna ), ska överlämningen av uppdraget ske kostnadsfritt för Beställaren. Det ska vara möjligt att teckna avtal på fast antal timmar per månad i syfte att säkerställa tillgänglighet. | C46: Ska-krav
A47: 7.4.8 | B47: Vid beställning av fastprisuppdrag ska priset inte överstiga pris för uppskattat antal timmar för konsulttjänster enligt Bilaga Pris p.3.1-3.2. Det överenskomna fasta priset gäller även om faktiskt antal timmar överstiger det uppskattade antal timmar. | C47: Ska-krav
A48: 7.4.9 | B48: Bekräftelse av de beställda konsultuppdragen ska vara skriftligt och innehålla minst antal timmar, konsultens namn/kompetens, uppdragets resultat, leveransdatum och budgetpris (alternativt fast pris) för uppdraget. Leverantören ska meddela i god tid om uppskattat antal riskerar överstigs, vilket måste godkännas av Beställaren. | C48: Ska-krav
A49: 7.4.10 | B49: Om inget annat överenskommes ska Leverantören kunna tillhandahålla konsult för utvecklings/förbättrings arbete (ej kopplat till support enligt Bilaga 6 SLA) inom tjugo (20) arbetsdagar. | C49: Ska-krav
A50: 7.5 | B50: Dokumentation
A51: 7.5.1 | B51: Leverantören ska vid införandet tillhandahålla en skriftlig dokumentation på svenska som beskriver hur IT-tjänsten är skyddad mot obehörig åtkomst, manipulation och intrång, för behöriga och obehöriga användare, skydd mot skadlig programvara och intrång. | C51: Ska-krav
A52: 7.5.2 | B52: Leverantören ska hålla en uppdaterad dokumentation på Beställarens tekniska uppsättningen av IT-tjänsten. | C52: Ska-krav
A53: 7.5.3 | B53: Användardokumentation och lathundar ska finnas både för Användare och Systemadministratörer av IT-tjänsten. Användarmanualerna ska vara anpassade efter användare och relevanta för de gränssnitt/eventuella applikationer de använder. | C53: Ska-krav
A54: 7.5.4 | B54: Systemdialoger och system- och användardokumentation ska vara på svenska. | C54: Ska-krav
A55: 7.5.5 | B55: Versionsuppdaterad användardokumentation ska finnas tillgänglig elektroniskt. | C55: Ska-krav
A56: 7.5.6 | B56: Det ska finnas en detaljerad systemdokumentation på svenska över Beställarens uppsättning av IT-tjänsten. Den ska minst innehålla: • Systembeskrivning/Modulbeskrivningar • Systemskiss • Dataflöden • Backup- och återställningsplan • Beroenden till andra eventuella komponenter och system där systemens dataflöden och krav på nätverk och kommunikationsportar tydligt framgår. • Backup- och återställningsplan som beskriver hur man uppfyller tillgänlighetskrav enligt Bilaga 6 Servicenivåer (SLA), inklusive hur man skyddar sig mot en ransomewareattack (i enlighet med Bilaga 3 Säkerhet) | C56: Ska-krav
A57: 7.5.7 | B57: Leverantören ska vid införandet tillhandahålla en skriftlig dokumentation på svenska som beskriver hur IT-tjänsten är skyddad mot obehörig åtkomst, manipulation och intrång, för behöriga och obehöriga användare, skydd mot skadlig programvara och intrång. | C57: Ska-krav
A58: 7.5.8 | B58: Samtlig dokumentation på systemlösningen ska överlämnas till Beställaren efter leveransgodkännande. | C58: Ska-krav
A59: 7.5.9 | B59: Dokumentationen ska uppdateras vid förändringar och överlämnas till Beställaren. | C59: Ska-krav
A60: 7.7 | B60: Support
A61: 7.7.1 | B61: Leverantören ska tillhandahålla servicenivåer i enlighet med vad som anges i Bilaga 6 - Servicenivåavtal (SLA) exklusive Innehåll i Tabell 2 Åtgärdstider stycke 2 och stycke 3 Tillgänglighet, krav kring dessa se 7.7.1.a-.7.7.1.e | C61: Ska-krav
A62: 7.7.1.a | B62: Leverantören ska tillhandahålla servicenivåer avseende åtgärdstid och tillhörande vite efter åtgärdstid i enlighet med vad som anges i Bilaga 6 - Servicenivåavtal (SLA) stycke 2 tabell 2 Åtgärdstider Kategori Kritisk | C62: Ska-krav
A63: 7.7.1.b | B63: Leverantören bör tillhandahålla servicenivåer avseende åtgärdstid och tillhörande vite efter åtgärdstid i enlighet med vad som anges i Bilaga 6 - Servicenivåavtal (SLA) stycke 2 tabell 2 Åtgärdstider Kategori Hög | C63: Bör-krav | E63: Enligt F63 | F63: =IF(D63=J63,600000,0) -> 0 | J63: ja
A64: 7.7.1.c | B64: Leverantören bör tillhandahålla servicenivåer avseende åtgärdstid och tillhörande vite efter åtgärdstid i enlighet med vad som anges i Bilaga 6 - Servicenivåavtal (SLA) stycke 2 tabell 2 Åtgärdstider samt Viten Kategori Medium. | C64: Bör-krav | E64: Enligt F64 | F64: =IF(D64=K64,250000,(IF(D64=L64,125000,0))) -> 0 | J64: nej | K64: ja, med åtgärdstid 36 timmar | L64: ja, med åtgärdstid 72 timmar
A65: 7.7.1.d | B65: Leverantören bör tillhandahålla servicenivåer avseende åtgärdstid och tillhörande vite efter åtgärdstid i enlighet med vad som anges i Bilaga 6 - Servicenivåavtal (SLA) stycke 2 tabell 2 Åtgärdstider Kategori Låg | C65: Bör-krav | E65: Enligt F65 | F65: =IF(D65=J63,30000,0) -> 0
A66: 7.7.1.e | B66: Leverantören bör tillhandahålla tillgänglighet i enlighet med vad som anges i Bilaga 6 - Servicenivåavtal (SLA) stycke 3 | C66: Bör-krav | E66: Enligt F66 | F66: =IF(D66=J63,500000,0) -> 0
A67: 7.7.2 | B67: Leverantörens servicedesk ska erbjuda felhantering såväl som stöd och rådgivning kring handhavande av IT-tjänsten. | C67: Ska-krav
A68: 7.7.3 | B68: Leverantören ska tillhandahålla en dedikerad kontaktperson till systemadministratörer. | C68: Ska-krav
A69: 7.7.4 | B69: Supporten ska vara bemannad under Normal arbetstid (8-17). | C69: Ska-krav
A70: 7.7.5 | B70: Frågor och felrapportering ska kunna rapporteras in via telefon samt via e-post alternativt ärendehanteringssystem. | C70: Ska-krav
A71: 7.7.6 | B71: Vid behov av support ska Leverantören kunna hantera detta via telefon och/eller med fjärranslutning under Normal arbetstid. | C71: Ska-krav
A72: 7.7.7 | B72: Supportpersonalen ska vara kompetent och serviceinriktad. | C72: Ska-krav
A73: 7.7.8 | B73: Leverantören ska kunna erbjuda en hög servicenivå med tydliga och mätbara tillgänglighetsnivåer. | C73: Ska-krav
A74: 7.7.9 | B74: Kostnad för support ska vara inkluderat i avtalspriset. | C74: Ska-krav
A75: 7.7.10 | B75: Leverantören ska erbjuda en bemannad svensktalande servicedesk som är tillgänglig via telefon, e-post och webbsida. | C75: Ska-krav
A76: 7.7.11 | B76: Leverantörens personal i servicedesken ska ha erfarenhet av att jobba med offererat system och har uppdaterad information om kundens IT-tjänst. | C76: Ska-krav
A77: 7.8 | B77: Test/Utbildning/Acceptans-miljö
A78: 7.8.1 | B78: Leverantören ska tillhandahålla minst en produktionsmiljö, utvecklingsmiljö och testmiljö. | C78: Ska-krav
A79: 7.8.2 | B79: Tjänsten ska innefatta möjligheten att testa funktionalitet, testa olika roller och hålla i utbildningar utan att behöva påverka produktionsmiljö genom tillgång till en så kallad Testmiljö och utbildningsmiljö. Testmiljön och utbildningsmiljön ska vara så identisk utifrån funktionalitet med produktionsmiljön som är praktiskt möjligt, inklusive gränssnitt och separerad från produktionsmiljön. | C79: Ska-krav
B80: Summa Börkravsavdrag | E80: =SUM(E5:E79) -> 0
D81: Summa Börkravspoäng: | E81: =SUM(E29:E66) -> 0
D82: Summa Avdrag för bör-krav SLA: | F82: =SUM(F63:F66) -> 0

Sheet 8. Tekniska
A1: ='1. Generellt'!A1 -> Ekonomisystem, UPP-2025/047 | C1: Anbudsgivare: | D1: =Information!D1 -> 0
A3: 8 | B3: Tekniska | C3: Typ av krav | D3: Uppfylls bör-kravet? | E3: Bör-kravet vikt/poäng | F3: Avdrag för uppfyllda bör-krav
A4: Nr | B4: Område/funktion
A5: 8.1 | B5: Roller och behörighet
A6: 8.1.1 | B6: Följande roller/antal bedöms för framtida användare i IT-tjänsten: Användare (antal aktiva användare ca 70st) Exempel på interna roller: Systemadministratörer (4) Ekonomiassistenter förvaltning Ekonomiassistenter centralt Ekonom/controller förvaltning Ekonom/controller centralt Handläggare Exempel på externa roller: Revisorer Applikationskonsulter, utöver leverantörens egna konsulter | C6: Ska-krav
A7: 8.1.2 | B7: IT-tjänsten ska minst klara angivet användarantal. | C7: Ska-krav
A8: 8.1.3 | B8: IT-tjänsten ska möjliggöra att under avtalstiden utöka med fler användare. | C8: Ska-krav
A9: 8.2 | B9: Systemadministration och behörighet
A10: 8.2.1 | B10: IT-tjänsten ska vara rollbaserad där olika roller ger olika behörighetsnivåer i IT-tjänsten. | C10: Ska-krav
A11: 8.2.2 | B11: Det ska gå att lägga till och bygga nya roller i IT-tjänsten. | C11: Ska-krav
A12: 8.2.3 | B12: Systemadministratören ska ha tillgång till att administrera IT-tjänsten. Systemadministratören ska ha tillgång till att skapa, ändra och radera IT-tjänstens användare och grupper. | C12: Ska-krav
A13: 8.2.4 | B13: Systemadministratören ska styra behörigheter (Som minst - läsa-, skriva-, uppdatera- och radera-behörigheter) för funktioner, moduler/processer och data så att respektive roll erhåller rätt behörighet. | C13: Ska-krav
A14: 8.2.5 | B14: Systemadministratör i Huddinge kommun ska ha tillgång att styra åtkomst till systemfunktioner samt av vilka användare de kan användas av. | C14: Ska-krav
A15: 8.2.6 | B15: En systemadministratör ska inte själv ha tillgång till att utöka sina egna behörigheter eller rättigheter. | C15: Ska-krav
A16: 8.2.7 | B16: Systemet ska ha funktion för att visa en översikt över roller och behörigheter i systemet, så att man enkelt kan se vilka grupper/personer som har vilka behörigheter | C16: Ska-krav
A17: 8.2.8 | B17: IT-tjänsten ska ha funktion för att utföra händelser enligt definierat tidsintervall | C17: Ska-krav
A18: 8.2.9 | B18: IT-tjänsten ska ha funktion att stänga/öppna bokföringsperioder manuellt och per automatik. | C18: Ska-krav
A19: 8.3 | B19: Integrationer
A20: 8.3.1 | B20: IT-tjänsten ska vara möjlig att integrera med andra verksamhetssystem genom väldokumenterade API:er | C20: Ska-krav
A21: 8.3.2 | B21: API:erna ska vara exponerade på ett sätt som möjliggör icke komplex integrering. | C21: Ska-krav
A22: 8.3.3 | B22: Integrationer ska vara möjlig att hanteras med Beställarens integrationsplattformar. Se bilaga 8– Beskrivning IT-miljö. | C22: Ska-krav
A23: 8.3.4 | B23: IT-tjänsten ska kunna integreras med Beställarens e-tjänsteplattform. Se bilaga 8 – Beskrivning IT-miljö. | C23: Ska-krav
A24: 8.3.5 | B24: IT-Tjänsten ska kunna integrera med Beställarens mailtjänst/E-post integration Se bilaga 8– Beskrivning IT-miljö. | C24: Ska-krav
A25: 8.3.6 | B25: IT-tjänsten ska kunna intregrera med komunens framtida-verktyg för logg och sårbarhetsanalys. | C25: Ska-krav
A26: 8.3.7 | B26: Leverantör ska på begäran kunna presentera en API-vy som tillhandahåller nödvändiga datamängder/informationsmängder för att Beställaren ska kunna bygga en fakturaportal för kundfakturor där kund ska kunna: se faktura, se status på faktura och kunna betala faktura. Arbete med att ta fram API-vyn ska påbörjas senast 60 dagar efter kunds begäran/beställning, därefter tar Beställaren tillsammans med leverantör fram nödvändiga detaljer för det fortsatta arbetet i form av en inledande förstudie. | C26: Ska-krav
A27: 8.3.8 | B27: Integrationer ska utgöra en väl fungerande helhet där systemen ska fungera tillsammans utan onödig manuell hantering. Information ska registreras på ett ställe och utbytas automatiskt mellan systemen via integrationer. | C27: Ska-krav
A28: 8.3.9 | B28: Data som Beställaren registrerat via manuell inmatning eller via integration i IT-tjänsten ska genom API’er kunna läsas, skrivas, uppdateras och raderas. | C28: Ska-krav
A29: 8.3.10 | B29: Inläsning av data ska kunna verifieras både utifrån innehåll och format. Fel som uppstår vid inläsning ska synliggöras i gränssnitt. | C29: Ska-krav
A30: 8.3.11 | B30: IT-tjänsten ska ha gränssnitt som visar: - Status - Resultat - Felmeddelande - Felkälla - Felorsak | C30: Ska-krav
A31: 8.3.12 | B31: IT-tjänsten ska ha gränssnitt för Systemadministratörer, Ekonomiassistenter centralt, Ekonom/controller centralt som för respektive integration visar: -nivå av allvarlighetsgrad. | C31: Bör-krav | E31: =IF(D31="JA",2,0) -> 0 | F31: =(Jämförelsesumma!$E$6/Jämförelsesumma!$F$6)*E31 -> 0 | H31: ja
A32: 8.3.13 | B32: Beställaren ska ha egen möjlighet att själv kunna ändra/komplettera och lägga till integrationer under hela avtalstiden. | C32: Ska-krav | H32: nej
A33: 8.3.14 | B33: Det bör inte krävas någon handpåläggning från leverantörens sida vid integrationsuppsättning | C33: Bör-krav | E33: =IF(D33="ja",4,0) -> 0 | F33: =(Jämförelsesumma!$E$6/Jämförelsesumma!$F$6)*E33 -> 0
A34: 8.3.15 | B34: Detta avser option som Beställaren har rätt (dock inte skyldighet)att nyttja under avtalsperioden. Om Beställaren så begär, ska Leverantören inom 30 dagar påbörja arbete med övergång från filöverföring till API för de system som är markerade med API i kolumn I i Bilaga 17 – Initiala integrationer Huddinge, förutsatt att respektive motpart/systemleverantör har förutsättningar för API-integration. Leverantören ska delta aktivt i framtagande av kravspecifikation och realisering för respektive integration Detta genomförs inom ramen av ett separat beställt konsultuppdrag till de timpriser som gäller för konsult enligt p.3.1-3.2 i flik "Pris". | C34: OPTION
A35: 8.4 | B35: Initiala integrationer
A36: 8.4.1 | B36: Samtliga initiala integration enligt bilaga ska ingå och realiseras under införandeprojektet. Se Bilaga 4 – Initiala integrationer Huddinge. | C36: Ska-krav
A37: 8.5 | B37: Import/Export
A38: 8.5.1 | B38: IT-tjänsten ska validera importerade filer/data på samma sätt som manuellt registrerat Data. | C38: Ska-krav
A39: 8.5.2 | B39: IT-tjänsten ska inom varje modul/process ha stöd för att importera och exportera filer i excel, csv, txt, xml, json, pdf m.fl. | C39: Ska-krav
A40: 8.5.3 | B40: IT-tjänsten ska ha stöd för att importera och exportera filer i SIE-format och liknande. | C40: Ska-krav
A41: 8.6 | B41: IAM (identitet och åtkomst)
A42: 8.6.1 | B42: Användaridentitet ska provisioneras och uppdateras löpande direkt eller indirekt från Beställarens metakatalog. Provisionering ska ske enligt någon av de tekniker som beskrivs i Bilaga IT-miljö (se Bilaga Beskrivning IT-miljö för info om Provisionering användaridentitet ) | C42: Ska-krav
A43: 8.6.2 | B43: Användarkonton ska inaktiveras automatiskt när en användare avslutar sin anställning via Beställarens metakatalog. | C43: Ska-krav
A44: 8.7 | B44: Inloggning och autentisiering
A45: 8.7.1 | B45: Alla användare ska autentiseras mot Beställarens IDP. Se bilaga 8 – Beskrivning IT-miljö. | C45: Ska-krav
A46: 8.7.2 | B46: IT-tjänsten ska ha stöd för inloggning med de autentiseringsmetoder som tillåts av Beställarens IDP. Se bilaga 8 – Beskrivning IT-miljö. | C46: Ska-krav
A47: 8.7.3 | B47: Inloggning ska ske genom tvåfaktorsinloggning för samtliga roller. | C47: Ska-krav
A48: 8.7.4 | B48: Varje användare ska ha ett unikt individuellt användarkonto (identitet) för att säkerställa att endast behöriga användare har tillgång till IT-tjänsten. | C48: Ska-krav
A49: 8.7.5 | B49: Användare ska bli automatiskt nedkopplade/utloggade efter viss tids inaktivitet. | C49: Ska-krav
A50: 8.7.6 | B50: Vid utloggning ska all behörighets- och sessionsinformation som lagras i t.ex. temporära filer i användarens dator rensas. Användaren ska själv erbjudas valet att aktivt avsluta sessionen. | C50: Ska-krav
A51: 8.7.7 | B51: Automatisk låsning av IT-tjänsten ska ske efter 20 misslyckade inloggningsförsök. Systemadministratör ska kunna låsa upp. | C51: Ska-krav
A52: 8.7.8 | B52: När person avslutar sin anställning hos Beställaren ska kontot och användardata tas bort från IT-tjänsten enligt GDPR, om inga andra lagkrav ställs. | C52: Ska-krav
A53: 8.8 | B53: Kommunikation
A54: 8.8.1 | B54: IT-tjänsten ska kommunicera krypterat (HTTPS eller TLS) | C54: Ska-krav
A55: 8.8.2 | B55: Certifikat till all kryptering ska tillhandahållas av leverantören om inte annat överenskommes. | C55: Ska-krav
A56: 8.8.3 | B56: IT-tjänsten ska ha stöd för tidssynkronisering med Network Time Protocol (NTP) | C56: Ska-krav
A57: 8.8.4 | B57: Namnuppslagning ska hanteras med secure DNS (Domain Name System) | C57: Ska-krav
A58: 8.8.5 | B58: IT-tjänsten ska stödja HTML 5 | C58: Ska-krav
A59: 8.8.6 | B59: IT-tjänsten ska stödja TCP IPv4 | C59: Ska-krav
A60: 8.8.7 | B60: IT-tjänsten ska kunna klara övergång till TCP IPv6. | C60: Ska-krav
A61: 8.9 | B61: Tillgång till IT-tjänsten
A62: 8.9.1 | B62: IT-tjänsten ska vara webbaserad. | C62: Ska-krav
A63: 8.9.2 | B63: IT-tjänsten ska ha responsiv design | C63: Ska-krav
A64: 8.9.3 | B64: IT-tjänstens alla funktioner ska fungera med moderna webbläsare såsom Microsoft Edge, Google Chrome, Firefox, Safari | C64: Ska-krav
A65: 8.9.4 | B65: IT-tjänsten ska ha full funktionalitet utan lokal programinstallation eller användning av insticksprogram för alla standard- och sällananvändare | C65: Ska-krav
A66: 8.9.5 | B66: Om behov av klient krävs för systemadministration ska denna del kunna hanteras genom fjärruppkoppling som leverantören ansvar för – Citrix eller dyligt med samma krav på authentisering | C66: Ska-krav
A67: 8.10 | B67: Samverkan med Huddinge kommuns tekninska miljö
A68: 8.10.1 | B68: IT-tjänsten ska vara kompatibel med Huddinge kommuns IT-infrastruktur. Huddinge kommuns tekniska miljö framgår av Bilaga 8 - Beskrivning IT-miljö. | C68: Ska-krav
A69: 8.10.2 | B69: Efter ett införande ska IT-tjänsten löpande anpassas för att fungera med nya versioner på enheter av komponenter, säkerhetsuppdateringar, patchar, servicepack till operativsystemet m.m. enligt gällande standard från Microsoft och andra större komponentleverantörer. Detta ska uppfyllas inom 6 månader från det att säkerhetsuppdateringar, patchar m.m. släpps från exempelvis Microsoft. | C69: Ska-krav
A70: 8.11 | B70: Underhåll och utveckling
A71: 8.11.1 | B71: Återkommande uppdateringar av IT-tjänsten ska ingå. | C71: Ska-krav
A72: 8.11.2 | B72: Leverantören ska bedriva ett kontinuerligt vidareutvecklingsarbete för IT-tjänsten. | C72: Ska-krav
A73: 8.11.3 | B73: Leverantören ska ha en inarbetad change management. | C73: Ska-krav
A74: 8.11.4 | B74: Information från Leverantören sker med god framförhållning vid underhåll av tjänsten. | C74: Ska-krav
A75: 8.11.5 | B75: Leverantören ska skriftligen informera användaren om vilka förändringar som avses göras inför en uppdatering av IT-tjänsten samt förklara vad förändringarna innebär. | C75: Ska-krav
A76: 8.11.6 | B76: Leverantören ska testa uppdateringar av IT-tjänsten innan dessa tillgängliggörs. | C76: Ska-krav
A77: 8.12 | B77: AI
A78: 8.12.1 | B78: Beställaren ska kunna ta del av funktioner för Generativ AI, Maskininlärning, Djupinlärning om dessa erbjuder mervärde till Beställaren | C78: Ska-krav
A79: 8.12.2 | B79: För ovansående funktioner/metoder (krav 8.12.1) ska IT-tjänsten ha funktion för att kunna särskilja av Beställaren sekretessmarkerad data och känsliga personuppgifter från övrig information innan information bearbetas | C79: Ska-krav
A80: 8.12.3 | B80: Om behandling sker i 3:e land eller publik molntjänst ska informationen först särskiljas enligt krav 8.12.2 | C80: Ska-krav
B81: Summa Börkravspoäng | E81: =SUM(E6:E80) -> 0

Sheet 9. Övriga
A1: ='1. Generellt'!A1 -> Ekonomisystem, UPP-2025/047 | C1: Anbudsgivare: | D1: =Information!D1 -> 0
A3: 9 | B3: Övriga krav | C3: Typ av krav
A4: Nr | B4: Område/funktion
A5: 9.1 | B5: Riktlinjer webbtillgänglighet
A6: 9.1.1 | B6: IT-tjänstens publika delar ska uppfylla krav på tillgänglighet enligt den harmoniserade europeiska standarden EN 301 549. Detta innebär att webbplatser och appar ska uppnå åtminstone nivå AA i version 2.1 av WCAG. Detta uppfylls genom att IT-tjänsten följer Myndigheten för digital förvaltnings (DIGG) vägledning för webbutveckling (anvisningarna som anges på http://www.webbriktlinjer.se). Ifylld checklista (https://webbriktlinjer.se/wcag/?checklista) samt en plan för åtgärdande av eventuella restpunkter ska redovisas på begäran. | C6: Ska-krav
A7: 9.2 | B7: Arkivering och gallring
A8: 9.2.1 | B8: I IT-tjänsten ska det vara möjligt att skilja på information som ska bevaras från information som ska gallras. | C8: Ska-krav
A9: 9.2.2 | B9: Teknisk funktion för gallring ska finnas i IT-tjänsten. | C9: Ska-krav
A10: 9.2.3 | B10: Gallring ska på Beställarens begäran kunna utföras i IT-tjänsten i enlighet med gallringsfrister som anges i gallringsbeslut. Gallringsfrister ska kunna ändras. | C10: Ska-krav
A11: 9.2.4 | B11: Planerad gallring ska dokumenteras i drifts- och förvaltningsplaner. | C11: Ska-krav
A12: 9.2.5 | B12: Föreskriven eller av Beställaren beslutad gallring (förstörande) av Beställarens information ska utan omfattande åtgärder kunna utföras vid valfri tidpunkt. | C12: Ska-krav
A13: 9.2.6 | B13: Resultat av begärd gallring ska kunna kontrolleras innan den utförs. | C13: Ska-krav
A14: 9.2.7 | B14: Gallring i IT-stödet ska inte ske om det medför risk för informationsförlust i handlingar som ska bevaras. | C14: Ska-krav
A15: 9.2.8 | B15: Gallringsrapport/gallringslogg ska kunna skapas i IT-stödet. Uppgifterna ska minst bestå av tidpunkt för gallring, vem som utfört gallringen och vad som gallrats. | C15: Ska-krav
A16: 9.2.9 | B16: Informationen ska fortlöpande (och vid valfri tidpunkt) kunna överföras till Beställarens e-arkiv enligt de tekniska krav som framgår av Riksarkivets författningssamling. | C16: Ska-krav
A17: 9.2.10 | B17: Informationen ska exporteras i en standardiserad paketstruktur, tex enligt Riksarkivets FGS eller likvärdig paketstruktur. | C17: Ska-krav
A18: 9.2.11 | B18: Export av Beställarens information ska inte medföra några tilläggskostnader för speciella exportverktyg, moduler eller liknande. | C18: Ska-krav
A19: 9.2.12 | B19: IT-tjänsten ska ha funktion för digital arkivering av utfärdade kundfakturor samt för bokföringsunderlag för verifikationer | C19: Ska-krav

Sheet Priser
A1: ='1. Generellt'!A1 -> Ekonomisystem, UPP-2025/047 | E1: Anbudsgivare: | F1: =Information!F1 -> 0
B3: Prispost | C3: Prisspecifikation enligt Bilaga Priser och betalning | D3: Specifikation (inklusive dock inte begränsat till) dessa krav och villkor | E3: Antal | F3: Enhet | G3: Pris | H3: Totalt
A4: 1 | B4: Införande (grundutförande) | C4: 2.1 | D4: enligt krav på införande enligt flik 7 "Införande och förvaltning", Bilaga Förslag på införandeplan samt p. 4 Avtal | E4: 1 | F4: styck | H4: =G4*E4 -> 0
A5: 2 | B5: IT-tjänst (grundutförande) | C5: 2.2 | D5: Samtliga upphandlingsdokument, se Kravspecifikation, Avtal, SLA, m.fl. | E5: 10 | F5: år | H5: =G5*E5 -> 0
A6: 3.1 | B6: Konsulttimmar, utöver införande (avseende utveckling, inkl. ev. framtida tillkommande optioner/integrationer, o.dyl.), för uppdrag som understiger 25 timmar eller de första 25 timmarna av respektive konsultuppdrag | C6: 2.3 | D6: enligt p.7.4.6-7.4.10 flik "Införande och förvaltning", p.8.3.18 flik 8 "Tekniska krav" | E6: 200 | F6: tim | H6: =G6*E6 -> 0
A7: 3.2 | B7: Konsulttimmar, utöver införande (avseende utveckling, inkl. ev. framtida tillkommande optioner/integrationer, o.dyl.), fr.o.m. den 25:e timmen inom ett specifikt konsultuppdrag | C7: 2.3 | D7: enligt p.7.4.6-7.4.10 flik "Införande och förvaltning", p.8.3.18 flik 8 "Tekniska krav" | E7: 50 | F7: tim | H7: =G7*E7 -> 0
A8: 4.1 | B8: Utbildning till systemadminstratörer (utöver utbildning under införande), heldag | C8: 2.4 | D8: enligt p.7.2.2-7.2.3 samt 7.2.5-7-2-7 flik "Införande och förvaltning", | E8: 10 | F8: styck | H8: =G8*E8 -> 0
A9: 4.2 | B9: Utbildning till slutanvändare (utöver utbildning under införande), heldag | C9: 2.4 | D9: enligt p.7.2.2-7.2.3 samt 7.2.5-7-2-7 flik "Införande och förvaltning", | E9: 10 | F9: styck | H9: =G9*E9 -> 0
G10: Anbussumma: | H10: =SUM(H4:H9) -> 0

Sheet Utv.Agilitet
A1: ='1. Generellt'!A1 -> Ekonomisystem, UPP-2025/047 | C1: Anbudsgivare: | D1: =Information!D1 -> 0
A2: Potential för IT-tjänstens agilitet kommer att utvärderas av Beställaren i enhlighet med 'Anbudsinbjudan' p.3.3.2.4
B3: Bedömning/poäng | C3: Beställarens kommentar | D3: Prisavdrag | G3: G
A4: Sammanlagd bedömning av agilitet utifrån Förslag på tjänstens genomförande | D4: =IF(B4="MVG",Jämförelsesumma!E8,(IF(B4=G4,Jämförelsesumma!E8/2,0))) -> 0 | G4: VG
G6: MVG | H6: MVG
A7: Bedömningen görs av Beställarens utvärderingsgrupp genom att tillämpa bedömningskriterierna och betygsskalan till den av anbudsgivaren ifylld Bilaga 15 Beskrivning av Agilitet

Sheet Utv.Användbarhet
A1: ='1. Generellt'!A1 -> Ekonomisystem, UPP-2025/047 | D1: Anbudsgivare: | E1: =Information!D1 -> 0
A2: Användbarhet kommer att utvärderas av Beställaren i enhlighet med 'Anbudsinbjudan' p.3.3.2.2 .
A3: Medelbetyg räknas fram utifrån de betyg de sätts i Bilaga 16 Utvärderingsscenarier Användbarhet
A4: Respektive medelbetyg räknas fram och anges nedan av Beställaren, med två (2) decimaler
A5: Nr | B5: Scenario | C5: Medelbetyg
A6: 1.1 | B6: Allmänt
A7: 1.2 | B7: Dynamiska sökningar
A8: 1.3 | B8: Hjälpfunktioner - FAQ el dyl
A9: 1.4 | B9: Hjälpfunktioner - text/lathundar
A10: 2.1 | B10: Perioder
A11: 2.2 | B11: Automatiskt stängning/öppning av perioder
A12: 2.3 | B12: Kontoplan och regler kopplat till våra konteringsdimensioner
A13: 2.3.a
A14: 2.3.b
A15: 2.3.c
A16: 2.4 | B16: Demostrera vilka möjligheter det finns i systemet för att sätta upp sambandskontroller
A17: 2.5 | B17: Bokföringorder
A18: 2.6 | B18: Periodisering
A19: 2.7 | B19: Trigger/automatisk (Samtliga koddelar)
A20: 3.1 | B20: Registrering av ny kund
A21: 3.1.a
A22: 3.1.b
A23: 3.1.c
A24: 3.2 | B24: Abonnemang
A25: 3.3 | B25: Fakturering
A26: 3.4 | B26: Inbetalningar
A27: 3.5 | B27: Avskrivning och nedskrivning av konstaterad kundförlust
A28: 3.6 | B28: Kravhantering
A29: 3.7 | B29: Utbetalning av kredit/tillgodosaldo
A30: 4.1 | B30: Leverantörsupplägg
A31: 4.1.a
A32: 4.1.b
A33: 4.1.c
A34: 4.1.d
A35: 4.1.e
A36: 4.2 | B36: Skapa betalfil
A37: 4.3 | B37: Definitivbokförd faktura
A38: 5.1 | B38: Skapa anläggning
A39: 5.2 | B39: Avskrivning av anläggning
A40: 5.3 | B40: Finansiell leasing
A41: 5.4 | B41: Ändring på anläggning
A42: 5.5 | B42: Avstämningar
A43: 5.6 | B43: Utrangering/Nedskrivning/försäljning
A44: 6.1 | B44: Nytt projekt
A45: 6.2 | B45: Aktivering
A46: 8.1 | B46: Användare
A47: 8.2 | B47: Användarregister
A48: 8.3 | B48: Integration/felrapporter
A49: 8.3.a
A50: 8.3.b
A51: 8.3.c
A52: 8.3.d
A53: 8.4 | B53: Dokumentarkiv
A54: 8.5 | B54: Import/Export
A55: 8.6 | B55: Händelseloggar
B56: Summa poäng användbarhet: | C56: =SUM(C6:C55) -> 0

Sheet Utv.Införandeplan
A1: ='1. Generellt'!A1 -> Ekonomisystem, UPP-2025/047 | D1: Anbudsgivare: | E1: =Information!D1 -> 0 | G1: 0
A2: Förutsättningar för smidigt och effektivt införande kommer att utvärderas av Beställaren i enhlighet med 'Anbudsinbjudan' p.3.3.2.3
C3: Bedömning/poäng | D3: Beställarens kommentar/motivering | E3: Prisavdrag | H3: G
B4: Sammanlagd bedömning av förslag på tjänstens införandeplan | E4: =IF(C4="MVG",Jämförelsesumma!E9,(IF(C4="VG ",Jämförelsesumma!E9/2,0))) -> 0 | H4: VG
H5: MVG
B12: Bedömningen görs av Beställarens utvärderingsgrupp genom att tillämpa bedömningskriterierna och betygsskalan till den av anbudsgivaren ifylld Bilaga 14 Förslag på införandeplan

Sheet Jämförelsesumma
A1: ='1. Generellt'!A1 -> Ekonomisystem, UPP-2025/047 | D1: Anbudsgivare: | E1: =Information!D1 -> 0
A2: Jämförelsesumma beräknas i enlighet med 'Anbudsinbjudan' p.3.4
B5: Anbudssumma | C5: =Priser!H10 -> 0 | E5: maximalt möljigt avdrag kvalitet | F5: Maximalt antal poäng/högst betyg | G5: Uppnått anta poäng/betyg
C6: =(G6/F6)*E6 -> 0 | D6: avdrag bör-krav funktionalitet | E6: 4000000 | F6: 53 | G6: ='1. Generellt'!E75+'3. Kundreskontra'!E109+'4. Leverantörsreskontra'!E40+'7. Införande och förvaltning'!E80+'8. Tekniska'!E81 -> 0
C7: ='7. Införande och förvaltning'!F63+'7. Införande och förvaltning'!F64+'7. Införande och förvaltning'!F65+'7. Införande och förvaltning'!F66 -> 0 | D7: avdrag bör-krav SLA | E7: 1380000
C8: =Utv.Agilitet!D4 -> 0 | D8: avdrag agilitet | E8: 500000 | F8: MVG | G8: =Utv.Agilitet!B4 -> 0
C9: =Utv.Införandeplan!E4 -> 0 | D9: avdrag införande | E9: 750000 | F9: MVG | G9: =Utv.Införandeplan!C4 -> 0
C10: =(G10/F10)*E10 -> 0 | D10: avdrag användbarhet | E10: 7000000 | F10: 66 | G10: =Utv.Användbarhet!C56 -> 0
B11: Jämförelsesumma | C11: =C5-C6-C7-C8-C9-C10 -> 0
